{
  "symbolique ADJ" : 0.9047,
  "appropriation NOM" : 1.8711,
  "dévaloriser VER:pper" : 1.1866,
  "médecin NOM" : 0.9762,
  "rigide ADJ" : 0.8571,
  "subordination NOM" : 6.512,
  "bouleversement NOM" : 1.6909,
  "merida NOM" : 1.6909,
  "phonologie NOM" : 3.9801,
  "néologisme NOM" : 0.9047,
  "visuellement ADV" : 2.0795,
  "produire VER:pres" : 0.4478,
  "conceptuel ADJ" : -0.2351,
  "calcul NOM" : 0.7277,
  "possibilité NOM" : 0.2169,
  "percentile NOM" : 10.8643,
  "bishop NOM" : 4.6003,
  "souhaitable ADJ" : 2.4817,
  "identifier VER:pper" : 2.1174,
  "présent NOM" : -0.1399,
  "intention NOM" : 0.7099,
  "conduire VER:infi" : 1.8564,
  "verbe NOM" : -1.9896,
  "infini ADJ" : 1.6909,
  "mesure NOM" : 0.376,
  "praxématique NOM" : 1.348,
  "psychique ADJ" : 1.1966,
  "normand ADJ" : 1.7254,
  "allégrement ADV" : 1.5282,
  "vision NOM" : 0.5545,
  "déficience NOM" : 1.444,
  "entraîner VER:ppre" : 1.3197,
  "romani NOM" : 1.6909,
  "consacrer VER:pper" : 1.2667,
  "reilly NOM" : 2.8577,
  "clinique ADJ" : 4.8872,
  "cible NOM" : 0.739,
  "constant ADJ" : 1.6033,
  "persistant ADJ" : 2.1032,
  "cellier NOM" : 1.348,
  "crucial ADJ" : 1.444,
  "vulnérable ADJ" : 1.9001,
  "intérieur NOM" : 0.4884,
  "seuil NOM" : 36.1532,
  "inconnu ADJ" : 0.5432,
  "répandre VER:pper" : 2.42,
  "produire VER:pper" : 0.5381,
  "attacher VER:pper" : 2.2899,
  "visée NOM" : 0.4644,
  "nécessairement ADV" : 0.3624,
  "sémanticien NOM" : 1.7254,
  "complet ADJ" : 0.3782,
  "coûteux ADJ" : 1.7072,
  "signe NOM" : 0.9135,
  "clitique ADJ" : 4.6085,
  "fonctionnel ADJ" : 0.5364,
  "tuller NOM" : 6.7065,
  "manque NOM" : 0.4971,
  "attribuer VER:pres" : 0.6442,
  "bailey NOM" : 2.5061,
  "cesse NOM" : 0.7909,
  "confronter VER:ppre" : 2.3355,
  "prestigieux ADJ" : 1.348,
  "évoquer VER:pper" : 2.2419,
  "diversifier VER:pper" : 0.912,
  "<.01 ADJ" : 1.3266,
  "corrélation NOM" : 1.3953,
  "lier VER:pper" : 0.846,
  "standardiser VER:pper" : 5.5714,
  "mélange NOM" : 3.6275,
  "relever VER:pper" : 1.0112,
  "fréquence NOM" : -0.4466,
  "apprendre VER:pper" : 0.5193,
  "prédominance NOM" : 2.3355,
  "henrichsen NOM" : 1.9577,
  "glossie NOM" : 1.348,
  "diffuser VER:pper" : 2.7543,
  "archétypique ADJ" : 3.4879,
  "nord-américain ADJ" : 1.348,
  "est-il ADJ" : 1.0359,
  "notion NOM" : -0.3366,
  "acquérir VER:pper" : 2.9655,
  "hamann NOM" : 2.5227,
  "haut ADJ" : 0.4059,
  "échec NOM" : 1.9133,
  "losh NOM" : 1.8749,
  "précédemment ADV" : 4.3856,
  "révéler VER:pres" : 1.8783,
  "visuel ADJ" : 2.0148,
  "déverbal NOM" : 0.5493,
  "pierre NOM" : 0.5636,
  "grammaire NOM" : -0.4847,
  "apprenant NOM" : 0.6504,
  "nucléaire ADJ" : 1.5513,
  "aspect NOM" : 0.2068,
  "rapprocher VER:impf" : 3.697,
  "obéir VER:pres" : 1.0427,
  "domaine-cible NOM" : 1.7254,
  "affecter VER:pres" : 1.6139,
  "lakoff NOM" : 1.7254,
  "cahier NOM" : 1.0427,
  "presse NOM" : 0.6172,
  "situer VER:pres" : 0.9034,
  "côtoyer VER:pres" : 1.4655,
  "apprendre VER:pres" : 1.741,
  "réunionnais NOM" : 1.6909,
  "enregistrer VER:pper" : 0.7304,
  "trop ADV" : 0.3267,
  "employer VER:infi" : 0.5373,
  "succès NOM" : 0.4772,
  "viol NOM" : 1.6909,
  "métaphorisation NOM" : 1.3992,
  "dépistage NOM" : 2.3222,
  "< ADJ" : 1.5634,
  "retrouver VER:pper" : 4.8872,
  "oral ADJ" : 3.2977,
  "accidentel ADJ" : 1.3129,
  "caractériser VER:infi" : 2.8684,
  "précédent ADJ" : 1.0278,
  "paradis NOM" : 1.5513,
  "essentiellement ADV" : 0.8404,
  "rapprocher VER:infi" : 1.4294,
  "omission NOM" : 1.0292,
  "assimiler VER:pres" : 2.5748,
  "morphologie NOM" : 0.252,
  "contraindre VER:pper" : 13.6735,
  "serait-il VER:cond" : 0.9881,
  "attendre VER:pres" : 1.6549,
  "lecte NOM" : 1.8039,
  "cibler VER:pper" : 2.5748,
  "réglementer VER:infi" : 3.4879,
  "zone NOM" : 0.8421,
  "identitaires ADJ" : 1.0865,
  "identifier VER:infi" : 4.1036,
  "nominal ADJ" : -0.2129,
  "raisonner VER:infi" : 2.4658,
  "fautif ADJ" : 4.1879,
  "raisonnement NOM" : 0.8858,
  "syntagme NOM" : -0.2063,
  "protocole NOM" : 1.3992,
  "bébé NOM" : 2.3696,
  "baser VER:ppre" : 2.4126,
  "correspondre VER:ppre" : 2.0325,
  "communiquer VER:infi" : 2.0942,
  "cognitivistes ADJ" : 1.3197,
  "déjà ADV" : 0.3774,
  "chose NOM" : 0.3472,
  "cristalliser VER:pper" : 4.1852,
  "acrolectale ADJ" : 1.4854,
  "entorse NOM" : 1.348,
  "appeler VER:pper" : 0.3026,
  "avérer VER:pper" : 2.398,
  "atteindre VER:infi" : 0.6952,
  "revue NOM" : 3.1525,
  "elfenbein NOM" : 2.5061,
  "hiérarchiser VER:pper" : 1.1312,
  "clitiques ADJ" : 3.8411,
  "rappeler VER:pres" : 0.9598,
  "<.05 ADJ" : 0.8284,
  "épreuve NOM" : 15.0311,
  "scott NOM" : 2.5061,
  "soit ADV" : 0.9297,
  "sorte NOM" : 0.8486,
  "complexité NOM" : 3.3822,
  "delage NOM" : 5.0411,
  "seul ADJ" : 0.4364,
  "créolophone ADJ" : 2.3696,
  "choix NOM" : -0.4317,
  "fixer VER:infi" : 5.0304,
  "bruer VER:infi" : 2.5061,
  "transfert NOM" : 0.6004,
  "riche ADJ" : 1.0745,
  "infériorisation NOM" : 1.348,
  "exception NOM" : 0.6216,
  "tard ADV" : 0.6698,
  "pouvoir VER:ppre" : 0.3811,
  "permanent ADJ" : 0.7999,
  "charles ADJ" : 2.4053,
  "épistémologique ADJ" : 0.8073,
  "maintenant ADV" : 0.4835,
  "voix NOM" : 0.8858,
  "domaine-source NOM" : 1.7254,
  "occuper VER:pres" : 0.3811,
  "citer VER:pper" : 2.2704,
  "suivant ADJ" : -0.2706,
  "meilleur ADJ" : 0.6009,
  "francophone ADJ" : 0.7323,
  "d ADJ" : 1.064,
  "suivre VER:ppre" : 1.9027,
  "déformer VER:pper" : 2.2711,
  "choisir VER:pres" : 1.6893,
  "substitution NOM" : 1.4374,
  "fergusonienne ADJ" : 1.6909,
  "camoufler VER:pres" : 1.348,
  "loban NOM" : 2.5061,
  "aire NOM" : 1.0462,
  "référer VER:pres" : 0.7099,
  "démontrer VER:infi" : 3.2824,
  "revenir VER:infi" : 1.0292,
  "évitement NOM" : 5.5659,
  "enchâssement NOM" : 2.8484,
  "réalité NOM" : 0.4779,
  "forger VER:pres" : 1.6909,
  "wulfeck ADJ" : 2.5061,
  "évaluer VER:pper" : 0.4994,
  "répercuter VER:pper" : 4.1852,
  "comprendre VER:ppre" : 2.5397,
  "taux NOM" : 5.932,
  "implication NOM" : 0.9047,
  "degré NOM" : 0.4932,
  "guillemot NOM" : 5.0304,
  "scolarité NOM" : 2.1454,
  "appartenir VER:infi" : 2.5061,
  "cf NOM" : -0.2525,
  "supposer VER:pres" : 0.4399,
  "offrir VER:pres" : 0.3068,
  "conceptualisation NOM" : 0.7856,
  "perte NOM" : 1.5193,
  "familier ADJ" : 0.6933,
  "interpréter VER:pper" : 1.0868,
  "dire VER:pres" : 0.2623,
  "ferguson NOM" : 2.2773,
  "devoir VER:cond" : 0.897,
  "restrictif ADJ" : 3.2776,
  "découler VER:pres" : 0.7685,
  "patient NOM" : -0.2337,
  "lichtman NOM" : 2.5061,
  "majorité NOM" : 1.0893,
  "agricole ADJ" : 0.8528,
  "acquisition NOM" : 0.4145,
  "inadéquat ADJ" : 1.348,
  "inférieur ADJ" : 1.0101,
  "reflet NOM" : 0.6316,
  "discursivement NOM" : 1.5513,
  "sémantique NOM" : -0.1891,
  "henry NOM" : 2.4897,
  "présence NOM" : 3.0536,
  "tranche NOM" : 1.1942,
  "extrait NOM" : 1.5701,
  "bilo NOM" : 10.988,
  "correspondre VER:pres" : -0.3397,
  "problématique ADJ" : 1.6139,
  "impliquer VER:ppre" : 1.8033,
  "khomsi NOM" : 1.9001,
  "affectif ADJ" : 0.696,
  "médical ADJ" : 0.7718,
  "france NOM" : 1.2634,
  "systématiquement ADV" : 0.614,
  "malentendant NOM" : 2.2058,
  "parvenir VER:futu" : 3.4879,
  "normal ADJ" : 6.6209,
  "dys NOM" : 1.348,
  "pôle NOM" : 2.2468,
  "patent ADJ" : 10.8643,
  "structure NOM" : 2.588,
  "agriculture NOM" : 0.6623,
  "affiner VER:pres" : 2.7883,
  "critiquer VER:infi" : 2.1488,
  "théorie NOM" : -0.4303,
  "famille NOM" : 2.6616,
  "stimuli NOM" : 1.348,
  "inégalité NOM" : 1.158,
  "cœur NOM" : 0.671,
  "jakubowicz NOM" : 5.4322,
  "disposer VER:impf" : 1.5758,
  "panel NOM" : 3.1985,
  "former VER:infi" : 0.879,
  "aberration NOM" : 3.4879,
  "dubois-charlier NOM" : 1.9577,
  "dénoncer VER:pres" : 1.348,
  "schum NOM" : 2.5061,
  "davis NOM" : 2.5061,
  "codage NOM" : 1.2765,
  "adjectif NOM" : -0.3779,
  "confiance NOM" : 1.0193,
  "léger ADJ" : 9.9973,
  "apparaître VER:infi" : 2.2419,
  "agir VER:infi" : 1.9621,
  "transplantation NOM" : 0.6316,
  "occurrence NOM" : -0.208,
  "quasi-totalité NOM" : 1.7634,
  "bénéficier VER:ppre" : 2.5061,
  "tardif ADJ" : 2.0844,
  "naturel ADJ" : 2.6026,
  "accusatif NOM" : 6.4597,
  "basilecte NOM" : 1.6909,
  "compensation NOM" : 4.7197,
  "bentler NOM" : 2.5061,
  "subir VER:infi" : 2.9404,
  "penser VER:infi" : 0.7685,
  "prédominer VER:ppre" : 2.1032,
  "intituler VER:pper" : 0.9096,
  "partager VER:pres" : 0.7569,
  "déficitaire ADJ" : 11.7642,
  "labial ADJ" : 2.5061,
  "difficile ADJ" : 0.4358,
  "règlement NOM" : 1.6909,
  "augmentation NOM" : 1.9292,
  "revisiter VER:pper" : 1.348,
  "écran NOM" : 0.4579,
  "conflit NOM" : 2.0508,
  "fondre VER:pres" : 1.8347,
  "subordonnée NOM" : 3.2704,
  "auditif ADJ" : 4.234,
  "volonté NOM" : 1.4896,
  "image NOM" : 0.5235,
  "auditivement NOM" : 2.5061,
  "outre ADV" : 0.7596,
  "confusion NOM" : 2.8609,
  "transversal ADJ" : 0.9564,
  "mésolectes NOM" : 1.8039,
  "traiter VER:pper" : 0.414,
  "hybridation NOM" : 1.1022,
  "provisoire ADJ" : 1.1817,
  "traduire VER:infi" : 0.4516,
  "paraître VER:pres" : 0.8672,
  "crago NOM" : 1.5513,
  "symons VER:pres" : 2.5061,
  "réceptif ADJ" : 1.7078,
  "porter VER:pres" : 0.2575,
  "briscoe NOM" : 4.6003,
  "dissociation NOM" : 2.229,
  "majeur ADJ" : 0.4281,
  "tenant NOM" : 2.1889,
  "induit ADJ" : 2.349,
  "régir VER:pper" : 0.7442,
  "abandonner VER:infi" : 2.3222,
  "certainement ADV" : 1.7379,
  "atypique ADJ" : 2.1615,
  "norbury NOM" : 4.6003,
  "dérouler VER:pres" : 3.1649,
  "bas ADJ" : 0.8701,
  "sévère ADJ" : 5.545,
  "u VER:simp" : 1.8419,
  "véhiculer VER:infi" : 1.1144,
  "adolescent ADJ" : 0.8835,
  "entraîner VER:pres" : 1.1144,
  "élaborer VER:pper" : 0.247,
  "construire VER:pper" : -0.1834,
  "critiquer VER:pper" : 1.348,
  "aborder VER:infi" : 0.6407,
  "dysglossie NOM" : 1.348,
  "combien ADV" : 1.0713,
  "paraître VER:pper" : 0.9911,
  "valide ADJ" : 2.2116,
  "consensus NOM" : 5.5247,
  "morphosyntaxe NOM" : 10.773,
  "ecart-type NOM" : 10.8643,
  "variabilité NOM" : 2.4257,
  "sourd ADJ" : 6.7491,
  "opposer VER:pper" : 0.6161,
  "informatiser VER:pper" : 1.5758,
  "agir VER:pres" : -0.5789,
  "répondre VER:ppre" : 0.8225,
  "score NOM" : 0.202,
  "cesser VER:pres" : 1.14,
  "linguistique NOM" : -0.1387,
  "juger VER:pper" : 0.559,
  "récuser VER:pres" : 1.6909,
  "finir VER:pper" : 1.5358,
  "exposer VER:pres" : 1.0676,
  "dit ADJ" : 2.0141,
  "utilisation NOM" : -0.5553,
  "respecter VER:ppre" : 1.0826,
  "faisceau NOM" : 1.0258,
  "hétérogénéité NOM" : 1.6007,
  "calquer VER:pper" : 1.644,
  "insécurité NOM" : 1.1817,
  "lacunaire ADJ" : 2.229,
  "critique ADJ" : 2.3558,
  "circonstanciel ADJ" : 2.1349,
  "similarité NOM" : 0.7458,
  "jeter VER:pres" : 1.6909,
  "bilan NOM" : 2.5838,
  "objectif ADJ" : 0.362,
  "imposer VER:pres" : 0.6014,
  "monjauze NOM" : 5.6134,
  "complexifier VER:pres" : 1.3944,
  "fergusoniens ADJ" : 1.348,
  "statutaire ADJ" : 1.348,
  "significativement ADV" : 2.379,
  "tuller VER:infi" : 2.5061,
  "sinding NOM" : 1.7254,
  "tributaire ADJ" : 2.265,
  "vocabulaire NOM" : 0.4697,
  "rejeter VER:pres" : 1.158,
  "préciser VER:pper" : 1.8102,
  "complétif ADJ" : 1.8977,
  "recenser VER:infi" : 2.5061,
  "domination NOM" : 2.6209,
  "mêler VER:infi" : 1.6909,
  "pronom NOM" : 0.7813,
  "diglossique ADJ" : 1.2449,
  "situer VER:ppre" : 6.2962,
  "johnson NOM" : 1.3407,
  "contrainte NOM" : 0.9899,
  "gillot NOM" : 2.5061,
  "contenter VER:infi" : 1.5513,
  "adopter VER:infi" : 7.697,
  "spontanément ADV" : 2.2058,
  "tout-venant NOM" : 1.2683,
  "ci-avant NOM" : 2.8,
  "peser VER:pres" : 3.6538,
  "bellugi NOM" : 1.6952,
  "regarder VER:pres" : 1.0325,
  "prégnance NOM" : 1.2997
}