{
  "typologie NOM" : 0.5707,
  "voir VER:pres" : 0.3475,
  "montrer VER:pper" : 0.7576,
  "emploi NOM" : 1.226,
  "constituer VER:ppre" : 0.4513,
  "librement ADV" : 13.16,
  "rigide ADJ" : 0.5555,
  "morceau NOM" : 0.8796,
  "exploiter VER:pres" : 0.3139,
  "traiter VER:infi" : 2.3328,
  "norme NOM" : 4.6804,
  "dérivationnels ADJ" : 0.5366,
  "probabilité NOM" : -0.2032,
  "robinson NOM" : 1.0431,
  "baser VER:pper" : -0.2756,
  "communément ADV" : 0.6738,
  "nécessaire ADJ" : -0.2378,
  "détailler VER:futu" : 1.0911,
  "indication NOM" : 0.5586,
  "arbitraire ADJ" : 5.5741,
  "modo ADV" : 1.0911,
  "règles NOM" : 0.995,
  "alonso ADJ" : 1.2086,
  "explicitation NOM" : 1.6128,
  "cours NOM" : -1.3137,
  "piquer VER:infi" : 1.2086,
  "smadja NOM" : 5.0535,
  "traduire VER:pper" : 0.3295,
  "invariabilité NOM" : 2.0979,
  "potentiel ADJ" : -0.187,
  "fig NOM" : 2.3078,
  "produire VER:pres" : 0.2093,
  "conceptuel ADJ" : -0.3998,
  "compter VER:pres" : -0.2636,
  "auxiliaire NOM" : 0.4639,
  "trouver VER:infi" : -0.4839,
  "tantôt ADV" : 1.0556,
  "calcul NOM" : -0.3124,
  "pièce NOM" : 0.691,
  "tristesse NOM" : 0.4988,
  "fontenelle NOM" : 0.9937,
  "université NOM" : 0.8144,
  "mal ADV" : 0.5677,
  "restreindre VER:pper" : 0.3979,
  "intex NOM" : 8.9245,
  "énormément ADV" : 6.1802,
  "domaine NOM" : -1.8977,
  "prendre VER:infi" : 1.5214,
  "reste NOM" : 0.6602,
  "reposer VER:ppre" : 3.1875,
  "identifier VER:pper" : -0.2959,
  "séduisant ADJ" : 0.6602,
  "mode NOM" : 0.4818,
  "orthographe NOM" : -0.5751,
  "disponible ADJ" : -0.4013,
  "aller VER:pres" : -0.8457,
  "différent ADJ" : -0.5968,
  "prototypique ADJ" : 4.4592,
  "perspective NOM" : 0.5202,
  "pratique NOM" : -1.2353,
  "présent NOM" : 1.1122,
  "normatif ADJ" : 0.6344,
  "attribuer VER:pper" : 0.5004,
  "munir VER:pper" : 1.1289,
  "désirer VER:pres" : 4.9484,
  "expliquer VER:futu" : 0.8333,
  "aiguiser VER:infi" : 1.9588,
  "dévorer VER:pper" : 0.7551,
  "mesure NOM" : -1.5966,
  "savoir VER:infi" : -0.3858,
  "éveiller VER:infi" : 0.9806,
  "projeter VER:pres" : 0.9937,
  "effroyable ADJ" : 17.2885,
  "dicouèbe NOM" : 1.2086,
  "multicritères ADJ" : 0.8511,
  "intelligence NOM" : 0.6445,
  "indispensable ADJ" : 0.6979,
  "lexicographique ADJ" : 1.6634,
  "nourriture NOM" : 0.808,
  "regrouper VER:pres" : 1.1861,
  "caractériser VER:pres" : 0.3518,
  "remettre VER:pper" : 0.709,
  "couvert ADJ" : 2.3971,
  "ntemps NOM" : 0.9558,
  "objet NOM" : -0.5446,
  "premièrement ADV" : 0.5171,
  "source NOM" : -0.6608,
  "construire VER:infi" : 0.256,
  "n2 NOM" : 0.6823,
  "accorder VER:infi" : 0.6939,
  "exploiter VER:pper" : 4.6351,
  "fini ADJ" : 1.3572,
  "jeanne NOM" : 1.0212,
  "grelep NOM" : 1.2832,
  "aborder VER:pper" : 0.4239,
  "pousser VER:pres" : 0.796,
  "pourtant ADV" : 2.9103,
  "absence NOM" : -0.2541,
  "constant ADJ" : 1.0063,
  "collecte NOM" : 1.2568,
  "*un ADJ" : 3.2142,
  "pertinent ADJ" : -0.668,
  "méprendre VER:pper" : 0.7806,
  "segond VER:ppre" : 1.9206,
  "ex ADV" : 0.7863,
  "circonscrire VER:pper" : 0.9937,
  "consister VER:pres" : -0.7208,
  "paramètre NOM" : -0.3905,
  "adapter VER:infi" : 0.3869,
  "maximal ADJ" : 0.4801,
  "renseigner VER:infi" : 1.8026,
  "lexique NOM" : -1.477,
  "générer VER:infi" : 0.9268,
  "conforme ADJ" : 0.9063,
  "présence/absence NOM" : 1.5649,
  "@a NOM" : 1.0507,
  "endroit NOM" : 0.5459,
  "amour NOM" : 0.2638,
  "apparaître VER:subp" : 0.7413,
  "fournir VER:pres" : 0.3256,
  "tâcher VER:pres" : 5.8548,
  "produire VER:pper" : -1.0696,
  "combinaison NOM" : 0.2558,
  "fusionner VER:pper" : 0.7806,
  "annoter VER:pper" : 4.6672,
  "décrire VER:infi" : -0.3843,
  "établissement NOM" : 1.968,
  "atteindre VER:pper" : -0.2051,
  "erreur NOM" : 0.4913,
  "visée NOM" : 1.8495,
  "nécessairement ADV" : -0.1883,
  "là ADV" : -0.2202,
  "nlieu NOM" : 0.9558,
  "constater VER:infi" : 0.3373,
  "conséquent ADJ" : 3.5459,
  "suivre VER:pper" : 0.282,
  "technique ADJ" : 1.6424,
  "performance NOM" : -0.8522,
  "dérivé NOM" : 8.5896,
  "notamment ADV" : 0.5128,
  "sensibiliser VER:infi" : 0.8557,
  "acquérir VER:pres" : 0.6319,
  "paradigme NOM" : 4.0399,
  "extraire VER:infi" : 0.9359,
  "énoncer VER:pper" : 1.3294,
  "nombreux ADJ" : 0.7465,
  "partiellement ADV" : 0.7344,
  "n1 NOM" : 0.5673,
  "sous-jacent ADJ" : 0.2424,
  "repérer VER:pper" : 3.2571,
  "froid ADJ" : 3.2571,
  "propriété NOM" : 6.2911,
  "synonymique ADJ" : 0.8204,
  "prêter VER:infi" : 3.2571,
  "préenregistré ADJ" : 0.7248,
  "paradigmatique ADJ" : 3.3278,
  "régulier ADJ" : -0.3484,
  "dorénavant ADV" : 1.2832,
  "rapide ADJ" : 1.0962,
  "évoquer VER:pper" : 0.3458,
  "expliquer VER:ppre" : 0.6082,
  "steele NOM" : 1.2086,
  "mourird'ennui NOM" : 1.5649,
  "historique NOM" : 0.6939,
  "éviter VER:infi" : 0.811,
  "psycholinguistique NOM" : 0.8947,
  "afficher VER:infi" : 0.7516,
  "énoncé NOM" : -3.4865,
  "objectif NOM" : -0.7564,
  "aborder VER:pres" : 2.4973,
  "réaliser VER:infi" : -0.2434,
  "souple ADJ" : 7.9914,
  "fréquence NOM" : -1.5989,
  "réel ADJ" : -0.505,
  "‘le VER:pres" : 1.8026,
  "variante NOM" : 3.2727,
  "considérer VER:pres" : -0.2898,
  "déviant ADJ" : 0.796,
  "finalisé ADJ" : 0.6059,
  "multidimensionnel ADJ" : 1.4163,
  "spontané ADJ" : -0.5599,
  "concentrer VER:pres" : 1.3064,
  "corps NOM" : 0.2516,
  "également ADV" : -0.3505,
  "proclit VER:simp" : 1.0507,
  "pouvoir VER:subp" : 0.7977,
  "sn NOM" : 2.0667,
  "chercheur NOM" : -0.2089,
  "communication NOM" : -0.9051,
  "figurer VER:pres" : -0.5203,
  "permettre VER:pper" : 0.7159,
  "nmoyen NOM" : 0.9558,
  "idiome NOM" : 2.5916,
  "papier NOM" : 0.6711,
  "garantir VER:pres" : 0.5037,
  "étiquette NOM" : -0.2102,
  "strictement ADV" : 0.4366,
  "notion NOM" : 0.9834,
  "massif ADJ" : 0.5021,
  "âme NOM" : 8.9245,
  "essentiel ADJ" : 1.8491,
  "guère ADV" : 2.6813,
  "un NOM" : -0.3256,
  "paralyser VER:pres" : 2.2146,
  "lemme NOM" : 2.7315,
  "côté NOM" : -0.4343,
  "organiser VER:pper" : 2.1412,
  "recenser VER:pres" : 1.0004,
  "exploitation NOM" : -0.1435,
  "prédiction NOM" : -0.9238,
  "robert NOM" : 0.3973,
  "mentionner VER:pper" : 0.2774,
  "haut ADJ" : 0.5288,
  "concerner VER:pres" : -0.6448,
  "tal NOM" : 0.7191,
  "explicatif ADJ" : 1.365,
  "capacité NOM" : -1.4517,
  "mot-clé NOM" : 0.7806,
  "géographique ADJ" : 0.8289,
  "noyau NOM" : 0.7158,
  "magn NOM" : 1.0911,
  "précédemment ADV" : 0.4174,
  "confronter VER:pper" : 0.5154,
  "voir VER:pper" : -0.4074,
  "à… NOM" : 0.8289,
  "spécifique ADJ" : -1.516,
  "constitution NOM" : 2.6389,
  "composition NOM" : 0.2896,
  "tableau NOM" : 0.2802,
  "base NOM" : 12.8953,
  "lien NOM" : 0.7274,
  "voir VER:futu" : 0.4458,
  "expliquer VER:infi" : 0.4188,
  "courant ADJ" : -0.2004,
  "registre NOM" : 0.6406,
  "meyer NOM" : 0.7313,
  "usage NOM" : -0.3907,
  "intégration NOM" : 0.2884,
  "précéder VER:pper" : 0.7379,
  "création NOM" : 0.2747,
  "fléchir VER:pper" : 0.6496,
  "lexicographe NOM" : 0.7257,
  "différence NOM" : -1.227,
  "obéir VER:pres" : 0.728,
  "kilgarriff VER:simp" : 5.0535,
  "presse NOM" : 0.3444,
  "guenthner NOM" : 0.8289,
  "devoir VER:futu" : 0.5653,
  "inespéré ADJ" : 1.3263,
  "permettre VER:subp" : 0.7413,
  "frantext NOM" : 1.7806,
  "processus NOM" : -0.2247,
  "décision NOM" : 10.0313,
  "écrit NOM" : -1.118,
  "apiculteur NOM" : 1.2086,
  "* ADJ" : 1.9497,
  "sclérose NOM" : 0.7694,
  "sous-classe NOM" : 0.3061,
  "pauvre ADJ" : 0.578,
  "secondaire ADJ" : 1.0685,
  "directement ADV" : 0.6157,
  "si ADV" : 0.3001,
  "broumley NOM" : 0.8289,
  "systématique ADJ" : -0.2847,
  "exprimer VER:infi" : 1.7921,
  "pondérer VER:ppre" : 1.0431,
  "périr VER:infi" : 1.5649,
  "éviter VER:ppre" : 3.6269,
  "dernier NOM" : 0.3131,
  "kombe ADJ" : 0.8289,
  "augmenter VER:infi" : 0.4214,
  "contenir VER:pper" : 0.419,
  "textesagnès ADJ" : 2.287,
  "supposer VER:ppre" : 4.0777,
  "étude NOM" : -1.9337,
  "fortement ADV" : 0.2284,
  "artificiel ADJ" : 0.3682,
  "concerner VER:pper" : 0.2079,
  "déterminant NOM" : -0.31,
  "jeu NOM" : -0.4165,
  "présent ADJ" : -0.5957,
  "caractériser VER:infi" : -0.137,
  "précédent ADJ" : 0.5133,
  "constituer VER:pres" : -0.7508,
  "rester VER:pper" : 0.8121,
  "locution NOM" : 0.4302,
  "reprendre VER:pres" : 0.5516,
  "dimension NOM" : 1.7243,
  "alonso NOM" : 0.9104,
  "comment ADV" : 0.3031,
  "intuitivement ADV" : 1.4571,
  "argument NOM" : 0.3328,
  "appeler VER:pres" : 0.3815,
  "clarkson NOM" : 1.0431,
  "montréal NOM" : 2.3971,
  "forme NOM" : -0.6404,
  "mixte NOM" : 5.0535,
  "dynamique ADJ" : 2.111,
  "rarement ADV" : 0.8178,
  "hausmann NOM" : 7.6582,
  "utile ADJ" : 0.5071,
  "partie NOM" : -0.2558,
  "décrire VER:pres" : 1.0291,
  "x VER:futu" : 0.8511,
  "func1 NOM" : 2.2146,
  "figement NOM" : 2.6325,
  "analogue ADJ" : 0.3023,
  "distributionnel ADJ" : -0.3271,
  "tirer VER:pper" : 3.6176,
  "local ADJ" : 5.8786,
  "part NOM" : -0.6652,
  "lettre NOM" : -1.4699,
  "formaliser VER:pres" : 0.8896,
  "cibler VER:pper" : 3.2007,
  "estime NOM" : 0.968,
  "application NOM" : 1.317,
  "avoir VER:ppre" : -0.3714,
  "commencer VER:pres" : 0.4857,
  "impossibilité NOM" : 0.9381,
  "autonome ADJ" : 0.5882,
  "aux_vpp NOM" : 1.0507,
  "nominal ADJ" : -0.3556,
  "causatif ADJ" : 0.7731,
  "auprès ADV" : 2.4511,
  "interactif ADJ" : 0.9877,
  "semi-figées ADJ" : 2.6325,
  "situation NOM" : -3.1179,
  "utilisateur ADJ" : -0.3645,
  "combinatoire NOM" : 19.5399,
  "zholkovski NOM" : 1.2086,
  "rosenfeld NOM" : 1.0431,
  "matiasek ADJ" : 1.0431,
  "changement NOM" : -1.1508,
  "disposer VER:infi" : 1.3451,
  "reconstituer VER:pper" : 1.0997,
  "monde NOM" : -0.6441,
  "tremblay VER:simp" : 0.9937,
  "base7 NOM" : 8.9245,
  "contextualiste ADJ" : 3.7123,
  "polysémique ADJ" : 0.2835,
  "x ADJ" : 0.8651,
  "mori NOM" : 1.0431,
  "prédicat NOM" : 0.7815,
  "essaim NOM" : 1.2086,
  "polysémie NOM" : -0.3455,
  "syntagme NOM" : -0.6569,
  "transparent ADJ" : 2.8464,
  "voir VER:infi" : 0.2803,
  "organisation NOM" : 0.8168,
  "*faire ADJ" : 7.6582,
  "dériver VER:infi" : 1.9146,
  "apparaître VER:ppre" : 6.3129,
  "couteau NOM" : 6.3224,
  "vice ADV" : 1.0744,
  "film NOM" : 5.776,
  "allemand NOM" : 0.8289,
  "valeur NOM" : 1.5319,
  "continuation NOM" : 0.8289,
  "longtemps ADV" : 0.3774,
  "arriver VER:infi" : 0.6881,
  "même ADV" : -1.8866,
  "mc NOM" : 1.9408,
  "étranger ADJ" : -0.185,
  "fréquent ADJ" : 2.7881,
  "envisageable ADJ" : 2.1257,
  "surtout ADV" : 0.3015,
  "versa ADV" : 1.0744,
  "place NOM" : -1.1862,
  "comporter VER:pres" : 0.4553,
  "sla NOM" : 0.7694,
  "collocationnelle ADJ" : 5.287,
  "niveau NOM" : -0.4001,
  "*vous NOM" : 3.2142,
  "jousse VER:pres" : 1.8892,
  "décrire VER:pper" : 2.8081,
  "comparable ADJ" : 0.3399,
  "apparition NOM" : 0.2638,
  "alm NOM" : 0.7152,
  "tabulaire ADJ" : 4.4925,
  "appeler VER:pper" : -0.2541,
  "pouvoir VER:pper" : 0.6038,
  "distinction NOM" : -0.3958,
  "école NOM" : 0.2864,
  "atteindre VER:infi" : -0.3368,
  "formel ADJ" : -0.4149,
  "isolément ADV" : 0.8421,
  "tirer VER:pres" : 0.9212,
  "typer VER:pres" : 0.808,
  "garder VER:infi" : 0.5969,
  "sortie NOM" : 2.2116,
  "catégorie NOM" : -2.5565,
  "hanks NOM" : 5.0535,
  "clitiques ADJ" : 0.3682,
  "habituel ADJ" : 0.6199,
  "étudier VER:pper" : 1.115,
  "absolu NOM" : 0.7658,
  "contexte NOM" : -0.6342,
  "développement NOM" : -0.8866,
  "sorte NOM" : 1.8061,
  "repérer VER:infi" : 0.8334,
  "complexité NOM" : -0.4028,
  "selva NOM" : 0.7313,
  "tradition NOM" : 0.7582,
  "plier VER:infi" : 0.7059,
  "direct ADJ" : 1.2173,
  "envisager VER:infi" : 0.2741,
  "définition NOM" : -0.7454,
  "seul ADJ" : -0.3006,
  "approche NOM" : -0.7729,
  "olst NOM" : 2.3971,
  "kahane NOM" : 0.9158,
  "choix NOM" : 3.9855,
  "idole NOM" : 3.2142,
  "tristesse… ADJ" : 1.1974,
  "fidèle ADJ" : 0.8204,
  "encodage NOM" : 1.673,
  "n3 NOM" : 1.9871,
  "hôtel NOM" : 1.8629,
  "appelé ADJ" : 4.3761,
  "graviter VER:pres" : 1.3578,
  "@b NOM" : 1.0507,
  "esprit NOM" : 0.2481,
  "revêtir VER:pres" : 0.5478,
  "étendue NOM" : 0.691,
  "exception NOM" : 0.9205,
  "qqun NOM" : 1.833,
  "éviter VER:pper" : 2.1425,
  "trigger NOM" : 0.8121,
  "respect NOM" : 1.7015,
  "sn ADJ" : 4.1265,
  "richardet NOM" : 1.5625,
  "sujet ADJ" : -0.5729,
  "représentation NOM" : -1.3466,
  "ontologie NOM" : 0.213,
  "sangloter VER:impf" : 1.0212,
  "wanner VER:infi" : 1.0827,
  "typique ADJ" : 0.5801,
  "facteur NOM" : -0.7863,
  "avis NOM" : 0.6656,
  "générique ADJ" : -0.574,
  "correspondre VER:futu" : 1.8566,
  "incepfunc1 NOM" : 2.2146,
  "aider VER:pper" : 0.8162,
  "génération NOM" : 0.2419,
  "apparaître VER:pper" : 0.7806,
  "maintenant ADV" : 0.2364,
  "suites NOM" : 0.3623,
  "fort ADV" : 0.804,
  "plein ADJ" : 1.1232,
  "axe NOM" : 1.9551,
  "penser VER:pres" : 0.9413,
  "court ADJ" : 2.1972,
  "comportement NOM" : 1.8206,
  "travail NOM" : -0.7926,
  "bipartition NOM" : 1.1655,
  "évident ADJ" : -0.1571,
  "flou ADJ" : 0.7516,
  "cooccurrence NOM" : 4.8366,
  "suivant ADJ" : 1.2346,
  "ci-dessous ADV" : 2.556,
  "communicationnelle NOM" : 1.7258,
  "gross/guenther VER:infi" : 2.8464,
  "considérer VER:infi" : -0.3171,
  "suivre VER:ppre" : 1.341,
  "d ADJ" : 1.7734,
  "organiser VER:infi" : 1.0953,
  "corriger VER:infi" : 0.4315,
  "donner VER:pres" : -0.4532,
  "désigner VER:ppre" : 0.3061,
  "guider VER:infi" : 1.1118,
  "déclencheur NOM" : 0.6711,
  "utiliser VER:infi" : 1.4838,
  "vie NOM" : -0.275,
  "portée NOM" : 0.3499,
  "grammaticaux.parmi VER:pper" : 1.5649,
  "amener VER:pper" : 0.3584,
  "souhaiter VER:pres" : 0.6678,
  "enseignant NOM" : 0.8915,
  "interroger VER:infi" : 0.3463,
  "appartenir VER:ppre" : -0.1367,
  "pouvoir VER:futu" : -0.3271,
  "grossmann NOM" : 1.2832,
  "faire VER:pper" : 0.468,
  "faiblesse NOM" : 0.3935,
  "action NOM" : 0.484,
  "puzzle NOM" : 1.3263,
  "condition NOM" : -0.5406,
  "causfunc1 ADJ" : 1.0911,
  "tendance NOM" : -0.3067,
  "statistique ADJ" : 2.852,
  "système NOM" : -0.8142,
  "expérience NOM" : -1.0096,
  "différentiel ADJ" : 0.2408,
  "illustrer VER:pper" : 1.004,
  "version NOM" : 0.2652,
  "magn ADJ" : 0.7059,
  "entièrement ADV" : 0.6629,
  "décroître VER:ppre" : 0.9051,
  "fondateur NOM" : 0.5797,
  "descendant ADJ" : 0.5839,
  "maison NOM" : 0.3373,
  "ajuster VER:ppre" : 1.1174,
  "cause NOM" : 0.5586,
  "anglais ADJ" : -1.69,
  "puisqu'elles ADJ" : 1.0072,
  "n4 NOM" : 1.9871,
  "langage NOM" : -2.4612,
  "enregistrement NOM" : 2.4274,
  "scénario NOM" : -0.2106,
  "seulement ADV" : -0.4207,
  "attribut NOM" : 1.2207,
  "toutefois ADV" : -0.2594,
  "bonheur NOM" : 0.7379,
  "étudiant NOM" : 0.3896,
  "bleue/ ADJ" : 1.5649,
  "cohérence NOM" : 1.3033,
  "grimer VER:pres" : 1.0141,
  "parcours NOM" : 0.6496,
  "focalisation NOM" : 1.5884,
  "verlinde ADJ" : 1.2832,
  "soumettre VER:pper" : 3.3754,
  "voie NOM" : 0.3979,
  "chagrin ADJ" : 0.8651,
  "sloc NOM" : 1.8975,
  "sensoriel ADJ" : 0.202,
  "choisir VER:pper" : 10.6179,
  "existence NOM" : 0.3475,
  "garantir VER:infi" : 2.0554,
  "passion NOM" : 0.5755,
  "véhiculer VER:pres" : 4.118,
  "parfaitement ADV" : 1.004,
  "introduire VER:ppre" : 0.808,
  "ainsi_que NOM" : 0.4251,
  "collègue NOM" : 0.5735,
  "donner VER:pper" : -0.4511,
  "tugwell NOM" : 5.0535,
  "savoir VER:pres" : 1.2028,
  "éviter VER:pres" : 0.9268,
  "modéliser VER:infi" : 0.7694,
  "estimer VER:pres" : 0.6222,
  "cf NOM" : 0.3866,
  "créer VER:infi" : 0.2828,
  "avenir NOM" : 0.796,
  "projeter VER:pper" : 2.1466,
  "offrir VER:pres" : -0.2487,
  "mine NOM" : 0.4988,
  "manipuler VER:ppre" : 2.2146,
  "retrouver VER:infi" : -0.147,
  "kombe NOM" : 1.2842,
  "production NOM" : -0.5802,
  "rendre VER:pres" : 0.3594,
  "accès NOM" : 0.5276,
  "autour ADV" : 0.6967,
  "présenter VER:futu" : 0.3764,
  "acceptabilité NOM" : 5.6093,
  "préciser VER:pres" : 0.4002,
  "modélisation NOM" : 1.6711,
  "illustrer VER:pres" : 1.115,
  "belgique ADJ" : 0.8698,
  "éventail NOM" : 2.0057,
  "rugby NOM" : 3.791,
  "identique ADJ" : 0.4832,
  "observation NOM" : -0.5431,
  "manifester VER:pres" : 3.3008,
  "livrer VER:futu" : 0.8289,
  "devoir VER:cond" : 0.412,
  "sélectionner VER:infi" : 0.5478,
  "sinclair NOM" : 2.5916,
  "prédéfinis ADJ" : 1.3819,
  "patient NOM" : -0.7344,
  "automatique ADJ" : -0.4907,
  "article NOM" : -0.6179,
  "général NOM" : 0.3537,
  "conclure VER:infi" : 0.4405,
  "format NOM" : 2.0453,
  "rédaction1 NOM" : 5.9861,
  "désormais ADV" : 0.8011,
  "ouvert ADJ" : 1.5625,
  "temps NOM" : 1.249,
  "@h NOM" : 1.0507,
  "élaboration NOM" : 3.0465,
  "adéquat ADJ" : 1.2627,
  "communal ADJ" : 1.8629,
  "étudier VER:ppre" : 0.9268,
  "compléter VER:infi" : 1.3415,
  "monolexémiques ADJ" : 1.4487,
  "utiliser VER:futu" : 0.4682,
  "falloir VER:futu" : 0.4801,
  "ludewig NOM" : 5.0535,
  "extension NOM" : 0.4958,
  "balle NOM" : 2.7688,
  "chemin NOM" : 7.5613,
  "défaite NOM" : 2.8464,
  "chat NOM" : 0.8,
  "partir VER:infi" : 0.9574,
  "affiner VER:pper" : 0.8466,
  "récemment ADV" : 0.3278,
  "extraction NOM" : 1.1854,
  "manipuler VER:infi" : 3.0382,
  "présence NOM" : -0.4323,
  "seconde NOM" : 0.5421,
  "formalisme NOM" : 0.5992,
  "travailler VER:infi" : 0.202,
  "vérifier VER:ppre" : 4.0106,
  "définir VER:pper" : -0.2888,
  "dictionnaire NOM" : 5.8278,
  "lisibilité NOM" : 0.7658,
  "utilisateur NOM" : -0.7578,
  "suffisamment ADV" : 0.6138,
  "tant ADV" : 1.5742,
  "discuter VER:pper" : 0.3902,
  "précis ADJ" : -0.2815,
  "traduction NOM" : -0.6013,
  "ensuite ADV" : -0.8749,
  "transducteur NOM" : 23.7245,
  "case NOM" : 4.6064,
  "correspondre VER:pres" : -0.6133,
  "mourir VER:infi" : 1.5649,
  "problématique ADJ" : 5.9108,
  "wright NOM" : 0.9158,
  "al ADJ" : -0.5385,
  "sous-champ NOM" : 1.1759,
  "descriptif ADJ" : 2.2833,
  "conversation NOM" : 0.3068,
  "impliquer VER:ppre" : 1.1893,
  "facile ADJ" : 0.3527,
  "long ADJ" : 0.257,
  "entrevue NOM" : 0.8289,
  "coder VER:infi" : 6.807,
  "vide ADJ" : 6.6934,
  "aujourd'hui ADV" : 0.2102,
  "sorties)6 NOM" : 3.5738,
  "pouvoir VER:infi" : -0.2012,
  "rédaction NOM" : 0.2582,
  "logiciel NOM" : -0.3738,
  "poser VER:pper" : 0.3,
  "clairement ADV" : 0.4174,
  "france NOM" : 0.254,
  "collocationnels ADJ" : 2.8464,
  "axer VER:pper" : 1.2086,
  "beaucoup ADV" : 0.2623,
  "ramos NOM" : 1.7806,
  "collocatifs ADJ" : 7.6582,
  "binaire ADJ" : 2.1205,
  "systématiquement ADV" : 3.3916,
  "ensemble ADV" : 5.7378,
  "brièvement ADV" : 0.6175,
  "étiqueter VER:infi" : 0.808,
  "relier VER:pper" : 3.3044,
  "manier VER:infi" : 2.3971,
  "sélectionner VER:ppre" : 0.728,
  "informer VER:pres" : 3.2142,
  "intéresser VER:ppre" : 0.3278,
  "mi-chemin ADV" : 1.0212,
  "relativisation NOM" : 1.6856,
  "p NOM" : -0.6028,
  "amer ADJ" : 2.8464,
  "disparaître VER:pres" : 0.6823,
  "déplacement NOM" : 0.6161,
  "message NOM" : -0.3759,
  "convention NOM" : 1.6303,
  "tendre VER:pres" : 3.2162,
  "faciliter VER:infi" : 0.2863,
  "xml NOM" : 3.5738,
  "systématiser VER:pres" : 1.2832,
  "dérivation NOM" : 0.7778,
  "fenêtre NOM" : 0.5478,
  "igor ADJ" : 1.2832,
  "sophistiqué ADJ" : 5.0535,
  "pédagogique ADJ" : 2.6439,
  "@e ADJ" : 1.0507,
  "*les ADJ" : 3.2142,
  "thème NOM" : -0.2922,
  "réussir VER:infi" : 0.9212,
  "section NOM" : -0.7315,
  "largement ADV" : 1.414,
  "structure NOM" : -1.9611,
  "saisir VER:pres" : 15.6254,
  "breidt NOM" : 6.0708,
  "plier VER:pper" : 0.8289,
  "séparer VER:infi" : 0.8845,
  "proche ADJ" : -0.5567,
  "‘articles NOM" : 1.4695,
  "douleur NOM" : -0.2214,
  "couple NOM" : 1.1368,
  "syntaxe NOM" : 0.486,
  "colonne NOM" : 0.4924,
  "enfin ADV" : 1.2301,
  "disposer VER:pres" : -0.2012,
  "genre NOM" : -0.3624,
  "récurrence NOM" : 1.4478,
  "convaincre VER:infi" : 1.2971,
  "impliquer VER:pper" : 4.4638,
  "décider VER:pper" : 5.5053,
  "consultant NOM" : 2.8197,
  "lexicologie NOM" : 2.1051,
  "limiter VER:pper" : 0.389,
  "wordnet NOM" : 0.6683,
  "sélectionner VER:futu" : 2.8464,
  "effectuer VER:pper" : -0.1917,
  "mélancolie NOM" : 1.7663,
  "langue NOM" : -5.5754,
  "analyser VER:pper" : 1.5258,
  "peur/avoir VER:infi" : 1.5649,
  "segond VER:simp" : 4.5309,
  "soupçon NOM" : 1.0911,
  "grand ADJ" : -0.656,
  "grammatical ADJ" : -0.7878,
  "présenter VER:infi" : -0.1447,
  "classement NOM" : 1.0609,
  "discours NOM" : 0.5125,
  "indépendant ADJ" : 0.3329,
  "prose NOM" : 2.2146,
  "ville NOM" : 0.2358,
  "texte NOM" : 1.577,
  "susceptible ADJ" : -0.2949,
  "cohérent ADJ" : 0.6442,
  "point NOM" : -0.2686,
  "institut NOM" : 1.6667,
  "voire ADV" : 0.4143,
  "adjectif NOM" : -0.2887,
  "copestake NOM" : 1.1203,
  "@i NOM" : 1.0507,
  "tal VER:futu" : 2.8368,
  "falloir VER:pres" : 0.6986,
  "cogénération NOM" : 1.5625,
  "figure NOM" : 4.8744,
  "parfois ADV" : -0.3577,
  "tlfi NOM" : 2.1425,
  "variable ADJ" : 0.3537,
  "occurrence NOM" : -1.3298,
  "rencontrer VER:infi" : 0.388,
  "systématisation NOM" : 1.0911,
  "drôle ADJ" : 4.5041,
  "sémantico-lexicales ADJ" : 1.0911,
  "chercher VER:pres" : -0.1551,
  "naturel ADJ" : -0.18,
  "servir VER:pres" : 0.4322,
  "syntaxiques2 ADJ" : 1.5649,
  "causation NOM" : 1.0911,
  "stochastique ADJ" : 0.4432,
  "époque NOM" : 0.3816,
  "alors ADV" : 0.3182,
  "gaieté NOM" : 1.0898,
  "économe ADJ" : 2.3971,
  "entretenir VER:pres" : 0.4025,
  "mc ADJ" : 8.7803,
  "aimer VER:cond" : 2.0979,
  "formule NOM" : 0.2238,
  "venir VER:pres" : -0.4114,
  "limiter VER:pres" : 1.2704,
  "difficulté NOM" : -1.5584,
  "kuhn NOM" : 1.0431,
  "actant NOM" : 0.7358,
  "grisé NOM" : 1.0507,
  "actanciel ADJ" : 1.9928,
  "avantage NOM" : -0.1862,
  "difficile ADJ" : 0.8216,
  "éclat NOM" : 1.0911,
  "électronique ADJ" : 1.0231,
  "façon NOM" : 0.5361,
  "très ADV" : -0.4328,
  "réutiliser VER:pper" : 0.6549,
  "n_source_affect NOM" : 2.2225,
  "ci-dessus ADV" : 0.2582,
  "sens NOM" : 0.5627,
  "causfunc1 NOM" : 1.0911,
  "hyperonyme NOM" : 4.7193,
  "amélioration NOM" : 0.6311,
  "contre NOM" : 0.3123,
  "récent ADJ" : -0.3645,
  "dafles NOM" : 1.6579,
  "ainsi_que ADJ" : 1.2028,
  "particulièrement ADV" : -0.4119,
  "groupe NOM" : -0.9899,
  "aller VER:infi" : 0.2516,
  "code NOM" : 0.4237,
  "church ADJ" : 3.8319,
  "perspectif ADJ" : 1.0479,
  "indirect ADJ" : 0.4315,
  "écran NOM" : 0.2169,
  "sabatier NOM" : 0.7413,
  "expliciter VER:pres" : 0.6823,
  "grosso ADV" : 1.0911,
  "pal NOM" : 1.0431,
  "n NOM" : 0.5757,
  "servir VER:pper" : 2.4223,
  "lexie NOM" : 9.2442,
  "créer VER:pper" : 2.3626,
  "syntagmatique ADJ" : 3.2571,
  "pointer VER:infi" : 0.7346,
  "sembler VER:pres" : 0.4584,
  "statique ADJ" : 1.9714,
  "modéliser VER:pper" : 0.5735,
  "outre ADV" : -0.2903,
  "faire VER:infi" : 3.3387,
  "indissociable ADJ" : 3.7123,
  "modif_post_n NOM" : 1.0507,
  "ligne NOM" : -0.265,
  "repèrera VER:futu" : 1.0507,
  "rendre VER:ppre" : 2.897,
  "bon ADJ" : -0.3643,
  "regrouper VER:infi" : 1.4857,
  "général ADJ" : -0.8282,
  "initiation NOM" : 1.2971,
  "enseignement NOM" : -0.2805,
  "diffus ADJ" : 0.8247,
  "sport NOM" : 2.9318,
  "aussi ADV" : -1.431,
  "correspondant ADJ" : 0.4526,
  "non-respect NOM" : 2.2938,
  "collocatif NOM" : 17.8844,
  "évidence NOM" : -0.8018,
  "statuer VER:infi" : 6.1337,
  "fait NOM" : -1.8111,
  "fl ADJ" : 3.1235,
  "williams NOM" : 3.7123,
  "paraître VER:pres" : 0.78,
  "passif ADJ" : 0.2905,
  "mêler VER:ppre" : 1.4487,
  "présupposé NOM" : 0.494,
  "être VER:pper" : -0.7479,
  "compiler VER:pper" : 0.7658,
  "santé NOM" : 0.8204,
  "significatif ADJ" : -0.5519,
  "commune NOM" : 1.1008,
  "sélectionner VER:pper" : 0.2233,
  "noter VER:pres" : 0.2174,
  "satisfaisant ADJ" : 0.6174,
  "table NOM" : 17.4933,
  "textuel ADJ" : 2.4191,
  "statut NOM" : 0.352,
  "classification NOM" : 1.085,
  "crever VER:infi" : 1.5649,
  "uniquement ADV" : 0.4607,
  "tremblay VER:pper" : 0.9937,
  "prendre VER:pper" : -0.2647,
  "petit ADJ" : -0.6644,
  "élève NOM" : -0.2906,
  "encore ADV" : -0.9838,
  "‘source NOM" : 0.3848,
  "f VER:simp" : 1.0911,
  "reposer VER:pres" : 0.7014,
  "chevron NOM" : 1.0507,
  "lexicologique ADJ" : 0.6199,
  "cadre NOM" : -0.718,
  "régir VER:pper" : 0.454,
  "sélection NOM" : -0.3591,
  "rire VER:infi" : 1.0911,
  "conjugué ADJ" : 1.6856,
  "synonyme ADJ" : 3.3584,
  "permettre VER:futu" : 6.7401,
  "heid NOM" : 3.7458,
  "symbolique NOM" : 5.0535,
  "différencier VER:infi" : 0.4392,
  "affiner VER:infi" : 1.7799,
  "révèleront VER:futu" : 0.9937,
  "inductif ADJ" : 2.9936,
  "*sa VER:simp" : 1.4914,
  "défi NOM" : 1.3333,
  "complémentarité NOM" : 2.8464,
  "vue NOM" : 0.4448,
  "manipuler VER:pper" : 3.4677,
  "augmenter VER:pres" : 0.2781,
  "productif ADJ" : 0.327,
  "plan NOM" : 0.5018,
  "idée NOM" : 0.3247,
  "requête NOM" : 1.698,
  "ins VER:pper" : 3.5738,
  "principalement ADV" : 4.2246,
  "v NOM" : 9.0843,
  "encoder VER:infi" : 1.7668,
  "attention NOM" : 0.6161,
  "assaillir VER:infi" : 1.0507,
  "exploiter VER:infi" : 0.3682,
  "mauvais NOM" : 7.6582,
  "thierry NOM" : 1.6221,
  "construire VER:pper" : -0.2975,
  "traiter VER:subp" : 1.4341,
  "aborder VER:infi" : 1.7049,
  "regrouper VER:ppre" : 1.3946,
  "autant ADV" : 0.9414,
  "*interroge VER:pres" : 7.6582,
  "être VER:subp" : 0.2645,
  "annoter VER:infi" : 1.2442,
  "indépendamment ADV" : 0.4214,
  "manifester VER:infi" : 1.7522,
  "amyotrophique ADJ" : 0.7694,
  "gain NOM" : -0.1378,
  "produire VER:infi" : -0.2332,
  "brophy NOM" : 0.8289,
  "modification NOM" : 0.4988,
  "total NOM" : 1.2698,
  "composante NOM" : -0.152,
  "déboucher VER:futu" : 5.9861,
  "scolaire ADJ" : 0.737,
  "ici ADV" : -0.4804,
  "unitaire ADJ" : 1.6423,
  "exercice NOM" : 0.2821,
  "sélectionner VER:pres" : 0.4071,
  "discussion NOM" : 0.5151,
  "variabilité NOM" : 3.3032,
  "remettre VER:infi" : 0.4909,
  "composer VER:pper" : -0.6951,
  "hétérogène ADJ" : 0.4862,
  "ancrer VER:pper" : 0.6082,
  "inspirer VER:pper" : 2.2822,
  "connaissance NOM" : -0.7789,
  "sujet NOM" : -1.6419,
  "ainsi ADV" : 0.8176,
  "structuration NOM" : 0.8259,
  "didactique ADJ" : 5.4988,
  "foncièrement ADV" : 4.5309,
  "latéral ADJ" : 0.6711,
  "associer VER:pres" : 0.6859,
  "répondre VER:ppre" : 1.3027,
  "agir VER:pres" : 0.4607,
  "fle NOM" : 1.6221,
  "occuper VER:infi" : 1.6221,
  "intensité NOM" : 1.5956,
  "suggérer VER:pper" : 0.8947,
  "développer VER:futu" : 0.7622,
  "caractérisation NOM" : 0.682,
  "générer VER:pper" : 2.0603,
  "nouveau ADJ" : -0.8179,
  "question NOM" : 0.2959,
  "traditionnel ADJ" : 0.2734,
  "compréhension NOM" : -0.2907,
  "position NOM" : -0.6106,
  "piste NOM" : 0.297,
  "proposer VER:futu" : 0.5206,
  "concept NOM" : -2.9194,
  "effet NOM" : -0.4209,
  "prédéfinies VER:pper" : 0.5839,
  "chercher VER:pper" : 0.2476,
  "appliquer VER:pres" : 0.6552,
  "abeille NOM" : 1.5584,
  "méthode NOM" : -1.6685,
  "unir VER:pres" : 4.776,
  "beurre NOM" : 2.3971,
  "identifiable ADJ" : 0.5947,
  "extrêmement ADV" : 0.2419,
  "original ADJ" : 0.3053,
  "table5 NOM" : 2.9941,
  "reproduction NOM" : 0.808,
  "donc ADV" : -1.6426,
  "viser VER:pres" : 0.7386,
  "classer VER:infi" : 0.6629,
  "émousser VER:infi" : 2.3971,
  "synonymie NOM" : -0.1424,
  "consultation NOM" : 11.4497,
  "critère NOM" : -1.4479,
  "dépit NOM" : 0.5839,
  "série NOM" : -0.27,
  "jousse NOM" : 0.9937,
  "regroupement NOM" : 0.7674,
  "résulter VER:pres" : 0.3613,
  "ruche NOM" : 2.0057,
  "expliquer VER:pres" : -0.1638,
  "habileté NOM" : 0.7694,
  "qualifier VER:pres" : 1.1893,
  "facultatif ADJ" : 0.2801,
  "isoler VER:pres" : 1.5104,
  "intégrer VER:infi" : 1.0025,
  "élever VER:pper" : -0.3547,
  "indiquer VER:pper" : 1.4396,
  "analyser VER:infi" : 0.8278,
  "autosuffisant ADJ" : 0.8121,
  "vérifier VER:pper" : 0.6683,
  "adjectif ADJ" : -0.6546,
  "courir VER:ppre" : 1.3097,
  "suite NOM" : 0.4275,
  "présenter VER:pper" : -0.286,
  "dégager VER:infi" : 0.3518,
  "importance NOM" : -0.3319,
  "lemmatiser VER:pper" : 2.1626,
  "donnée NOM" : 6.7951,
  "connaître VER:infi" : 4.3761,
  "avoir VER:cond" : 4.2691,
  "illico ADV" : 0.8289,
  "concurrent ADJ" : 1.5571,
  "totalement ADV" : -0.1646,
  "anticiper VER:infi" : 6.4299,
  "tour NOM" : 1.409,
  "violemment ADV" : 1.0507,
  "rapport NOM" : -2.4732,
  "relationnel ADJ" : 0.6753,
  "composer VER:pres" : 0.2052,
  "mettre VER:pper" : -0.3623,
  "environnement NOM" : 0.2419,
  "permettre VER:infi" : 0.5787,
  "mise NOM" : -0.4604,
  "cinquième ADJ" : 0.7586,
  "nature NOM" : -0.5251,
  "métaphore NOM" : 0.2768,
  "libre ADJ" : 0.2476,
  "recourir VER:infi" : 0.8376,
  "désir NOM" : 1.536,
  "mini-sémanticiens NOM" : 0.9806,
  "‘qualité NOM" : 1.0505,
  "confronter VER:infi" : 0.8511,
  "ordre NOM" : 0.3445,
  "pionnier NOM" : 1.2442,
  "exprimer VER:pres" : -0.2327,
  "présentation NOM" : 1.9248,
  "*une NOM" : 0.8747,
  "concerner VER:ppre" : -0.3908,
  "-ci ADV" : -0.8687,
  "terme NOM" : -4.0201,
  "intégrer VER:ppre" : 3.8457,
  "nécessité NOM" : -0.1435,
  "vocabulaire NOM" : 0.6418,
  "entreprendre VER:pper" : 0.796,
  "apprentissage NOM" : -0.6814,
  "dernier ADJ" : 0.3493,
  "passivation NOM" : 0.9877,
  "expliquer VER:pper" : 0.484,
  "maîtrise NOM" : 0.2159,
  "percevoir VER:pper" : 2.4291,
  "tutin NOM" : 1.4571,
  "scène NOM" : -0.1804,
  "nrésultat NOM" : 1.9871,
  "qualifier VER:pper" : 0.5053,
  "lâche ADJ" : 2.9624,
  "et/ou ADJ" : 0.4726,
  "observer VER:pres" : -0.3128,
  "indiquer VER:pres" : 0.4743,
  "préciser VER:pper" : 1.1956,
  "régime NOM" : 1.4739,
  "aux_ver NOM" : 1.0507,
  "présenter VER:pres" : 7.4423,
  "dénoter VER:ppre" : 1.8975,
  "important ADJ" : -1.68,
  "n_affect NOM" : 0.2188,
  "étroit ADJ" : 2.9993,
  "problème NOM" : 0.761,
  "français>danois ADJ" : 2.3971,
  "pronom NOM" : -0.4929,
  "puis ADV" : 0.717,
  "trouver VER:pres" : 0.3854,
  "amateur NOM" : 3.2142,
  "variété NOM" : -0.4976,
  "situer VER:ppre" : 0.9051,
  "demander VER:pper" : 2.8011,
  "permettre VER:ppre" : 1.8576,
  "exister VER:pres" : -0.617,
  "prendre VER:ppre" : 0.2364,
  "être VER:futu" : 1.8821,
  "laf NOM" : 1.2832,
  "pasero NOM" : 0.7413,
  "conserver VER:pres" : 0.7622,
  "imposer VER:pper" : 5.0266,
  "talksback NOM" : 0.8289,
  "principe NOM" : 0.4481,
  "globalement ADV" : 0.3107,
  "fixe ADJ" : 4.6522,
  "automatiquement ADV" : 2.6537,
  "consécutif ADJ" : 1.2592,
  "cache NOM" : 1.5412,
  "suppléance NOM" : 0.3764,
  "notable ADJ" : 1.0664,
  "loisir… ADJ" : 0.8289,
  "bourdonner VER:infi" : 1.2086,
  "baroni ADJ" : 1.0431,
  "football NOM" : 2.7314,
  "résultat NOM" : -4.7738,
  "théorique ADJ" : -0.6624,
  "consulation NOM" : 0.9937,
  "formation NOM" : -0.152,
  "patron NOM" : 0.6654,
  "accéder VER:infi" : 0.844,
  "passivable ADJ" : 1.7316
}