{
  "goldberg NOM" : 1.6871,
  "passif NOM" : 1.5027,
  "emploi NOM" : 0.6611,
  "instancié ADJ" : 5.0599,
  "dynamique NOM" : 1.2539,
  "définir VER:pres" : 0.7245,
  "stocker VER:pper" : 1.3179,
  "hypothèse NOM" : -0.2457,
  "préciser VER:pres" : 2.4098,
  "perl NOM" : 2.2794,
  "illustrer VER:pres" : 0.6053,
  "baser VER:pper" : 0.328,
  "propre ADJ" : -0.1853,
  "productivité NOM" : 0.7037,
  "préposition NOM" : 5.1192,
  "commun ADJ" : 15.2651,
  "conclure VER:infi" : 5.7887,
  "information NOM" : -0.2784,
  "programme NOM" : 0.6734,
  "porter VER:ppre" : 0.6131,
  "déconstruire VER:infi" : 2.6061,
  "principal ADJ" : 0.2943,
  "nettoyage NOM" : 2.4303,
  "que ADV" : 0.6415,
  "doudou NOM" : 1.6871,
  "identifier VER:pper" : 0.5886,
  "comparaison NOM" : 0.5012,
  "différent ADJ" : 2.5,
  "différencier VER:pper" : 1.4557,
  "instanciation NOM" : 5.0599,
  "intention NOM" : 1.0892,
  "couverture NOM" : 1.9795,
  "sembler VER:pper" : 2.6061,
  "comme ADV" : 0.38,
  "dénombrement NOM" : 2.4303,
  "expression NOM" : -0.3753,
  "mesure NOM" : -0.2015,
  "disparaître VER:pper" : 7.6788,
  "stable ADJ" : 0.7586,
  "seconde NOM" : 1.2295,
  "travailler VER:infi" : 0.7885,
  "idiomatique ADJ" : 1.5653,
  "noter VER:infi" : 2.0989,
  "étendre VER:pper" : 0.8972,
  "tant ADV" : 0.6627,
  "isoler VER:infi" : 1.8218,
  "précis ADJ" : 1.1001,
  "objet NOM" : 0.7305,
  "ensuite ADV" : 0.3287,
  "correspondre VER:pres" : 0.2929,
  "accorder VER:infi" : 1.4002,
  "forme/sens NOM" : 1.6871,
  "dire VER:pper" : 3.9494,
  "appuyer VER:pres" : 0.5392,
  "plus ADV" : 0.3398,
  "consister VER:pres" : 0.9763,
  "précision NOM" : 1.227,
  "appeler VER:infi" : 1.1127,
  "être VER:ppre" : 0.5742,
  "pouvoir VER:infi" : 0.6831,
  "logiciel NOM" : 0.9902,
  "séquence NOM" : -0.1431,
  "lexique NOM" : 0.2797,
  "association NOM" : 1.5921,
  "régi ADJ" : 4.6312,
  "analyse NOM" : -0.9943,
  "beaucoup ADV" : 3.4286,
  "apposition NOM" : 1.7642,
  "pas ADV" : -2.1601,
  "abstraction NOM" : 1.0802,
  "apparaître VER:pres" : 1.5625,
  "opération NOM" : 1.3696,
  "c'est-à-dire ADV" : 2.7037,
  "unité NOM" : 0.3178,
  "naturalité NOM" : 2.3955,
  "mieux ADV" : 0.4828,
  "relever VER:pres" : 1.3477,
  "numérique ADJ" : 1.6562,
  "linguistique ADJ" : -0.5537,
  "commande NOM" : 1.5464,
  "échelle NOM" : 0.6962,
  "recteur NOM" : 4.0432,
  "disparaître VER:pres" : 1.3874,
  "construction NOM" : 4.6963,
  "technique ADJ" : 0.4928,
  "déterminer VER:ppre" : 0.8349,
  "total ADJ" : 4.792,
  "quantitatif ADJ" : 2.1725,
  "notamment ADV" : 0.2522,
  "signe NOM" : 1.6262,
  "clitique ADJ" : 1.2106,
  "revanche NOM" : 0.4013,
  "prép NOM" : 1.3398,
  "perdre VER:pper" : 1.4557,
  "marcher VER:pres" : 2.3956,
  "syntaxe NOM" : 0.5177,
  "diessel NOM" : 1.6871,
  "input NOM" : 0.9262,
  "comparer VER:pres" : 1.0671,
  "signifié NOM" : 2.3357,
  "théorie NOM" : 2.774,
  "propriété NOM" : 2.2677,
  "pair ADJ" : 1.6218,
  "fragment NOM" : 1.2274,
  "non-accentuées ADJ" : 2.4303,
  "cacher VER:pper" : 1.1031,
  "vs NOM" : 2.2371,
  "force NOM" : 1.734,
  "considérant NOM" : 2.3336,
  "placer VER:pper" : 2.6214,
  "énoncé NOM" : -0.3569,
  "corrélation NOM" : 0.9353,
  "traitement NOM" : -0.1526,
  "argumentale ADJ" : 1.3153,
  "lier VER:pper" : 0.2651,
  "grammatical ADJ" : 0.2501,
  "présenter VER:infi" : 0.7637,
  "préférable ADJ" : 1.2608,
  "moins ADV" : 0.3538,
  "vis-à-vis ADV" : 2.5606,
  "séquenceur NOM" : 2.4303,
  "figurer VER:pres" : 0.4511,
  "supprimer VER:infi" : 1.4825,
  "vé VER:pper" : 1.6871,
  "corpus NOM" : 5.0032,
  "concret ADJ" : 1.9272,
  "être VER:impf" : 0.2287,
  "mesurer VER:infi" : 1.3644,
  "est-on ADJ" : 1.633,
  "occurrence NOM" : 0.6672,
  "notion NOM" : 2.2264,
  "complément NOM" : 0.4709,
  "naturellement ADV" : 2.0892,
  "un NOM" : 1.0438,
  "acquérir VER:pper" : 0.8012,
  "récupérer VER:infi" : 1.5418,
  "désigner VER:pres" : 1.945,
  "rection NOM" : 1.6273,
  "mot NOM" : -0.8996,
  "précédemment ADV" : 0.6734,
  "g1_2 NOM" : 4.1292,
  "cadiot NOM" : 1.8682,
  "référence NOM" : -0.2477,
  "préciser VER:infi" : 1.038,
  "sémantique/pragmatique ADJ" : 1.6871,
  "spécifique ADJ" : -0.1908,
  "tomasello NAM" : 1.2946,
  "test NOM" : 1.3872,
  "précisément ADV" : 0.3911,
  "hapax NOM" : 2.3336,
  "abstrait NOM" : 1.1291,
  "expansion NOM" : 16.1434,
  "base NOM" : -0.3546,
  "grammaire NOM" : 0.2247,
  "établir VER:pres" : 0.9212,
  "lien NOM" : 1.208,
  "autotest NOM" : 3.1966,
  "égarer VER:pper" : 2.5093,
  "usage NOM" : -0.2532,
  "milner NOM" : 2.0791,
  "précéder VER:pper" : 1.4483,
  "considérer VER:pper" : 3.0545,
  "spécification NOM" : 2.1898,
  "sémantique ADJ" : 0.9723,
  "augmentation NOM" : 2.7157,
  "carte NOM" : 2.9492,
  "sens NOM" : -0.673,
  "renvoi NOM" : 1.6002,
  "schématique ADJ" : 1.6871,
  "exister VER:ppre" : 1.4865,
  "permettre VER:pres" : 0.5815,
  "prédéterminant NOM" : 2.0634,
  "processus NOM" : 0.762,
  "récent ADJ" : 1.33,
  "saturer VER:infi" : 5.0599,
  "particulièrement ADV" : 0.5077,
  "modifieur NOM" : 1.6745,
  "antéposer VER:pper" : 1.467,
  "proposer VER:pper" : 0.2516,
  "proportion NOM" : 5.3865,
  "n NOM" : 3.4689,
  "syntagmatique ADJ" : 0.9574,
  "frontière NOM" : 0.8535,
  "étude NOM" : -0.2796,
  "outre ADV" : 0.5933,
  "faire VER:infi" : 0.5998,
  "langacker NOM" : 1.4236,
  "peu ADV" : 1.8494,
  "observer VER:infi" : 0.7251,
  "interpréter VER:infi" : 2.6911,
  "caractériser VER:infi" : 0.7769,
  "enfant NOM" : -0.7173,
  "constituer VER:pres" : 0.2582,
  "d'autre_part NOM" : 0.5412,
  "établir VER:infi" : 0.804,
  "dimension NOM" : 0.2509,
  "argument NOM" : 5.0857,
  "appeler VER:pres" : 0.647,
  "forme NOM" : 0.8996,
  "correspondre VER:infi" : 0.8721,
  "distinctes… ADJ" : 2.4303,
  "partie NOM" : -0.1638,
  "être VER:pper" : -0.6088,
  "mémoriser VER:pper" : 1.0892,
  "fonctionnement NOM" : 1.8601,
  "morphologique ADJ" : 0.6554,
  "significatif ADJ" : 1.1146,
  "tout ADV" : 0.407,
  "verbal ADJ" : 3.1859,
  "autorisation NOM" : 4.0659,
  "manière NOM" : 0.2043,
  "demander VER:pres" : 0.9202,
  "distinguer VER:pres" : 0.7448,
  "statut NOM" : 0.6246,
  "trouver VER:cond" : 1.6871,
  "uniquement ADV" : 0.7043,
  "stipule NOM" : 1.7491,
  "aller VER:ppre" : 1.36,
  "situation NOM" : 0.2921,
  "émerger VER:infi" : 1.1498,
  "pertinence NOM" : 0.7115,
  "emplacement NOM" : 1.5464,
  "instanciés VER:pper" : 5.6961,
  "biais NOM" : 0.6281,
  "progression NOM" : 0.9232,
  "gauche NOM" : 1.4594,
  "comparer VER:infi" : 0.7194,
  "augmenter VER:pres" : 4.9198,
  "productif ADJ" : 2.2188,
  "idée NOM" : 0.4321,
  "voir VER:infi" : -0.1432,
  "émission NOM" : 0.951,
  "travailler VER:pper" : 3.1748,
  "interprétatif ADJ" : 1.4305,
  "respectivement ADV" : 2.0209,
  "d'une_part NOM" : 0.6102,
  "construire VER:pper" : 0.4204,
  "prédicatif ADJ" : 2.7453,
  "normaliser VER:infi" : 2.4303,
  "convier VER:pres" : 1.3937,
  "même ADV" : -0.2405,
  "correspondre VER:ppre" : 0.5672,
  "spécialiser VER:pper" : 1.3441,
  "opérateur NOM" : 1.1848,
  "varier VER:pres" : 1.7304,
  "intéresser VER:pres" : 0.5824,
  "réciproquement ADV" : 1.4594,
  "réaliser VER:pres" : 0.7789,
  "surtout ADV" : 3.5731,
  "comporter VER:pres" : 4.0755,
  "droite NOM" : 2.0911,
  "but NOM" : 0.611,
  "emprunter VER:pper" : 1.0474,
  "schématisation NOM" : 3.0061,
  "français ADJ" : -0.5589,
  "ici ADV" : -0.2818,
  "majuscule NOM" : 1.7566,
  "bien ADV" : -0.3466,
  "sous-corpus NOM" : 22.1151,
  "appeler VER:pper" : 1.5164,
  "lexical ADJ" : -0.3448,
  "distinction NOM" : 0.5174,
  "ancrer VER:pper" : 2.9064,
  "accroissement NOM" : 3.5812,
  "ainsi ADV" : 0.3917,
  "hasard NOM" : 1.7962,
  "énonciatif ADJ" : 2.1472,
  "phonologique/syntaxique ADJ" : 1.6871,
  "associer VER:pres" : 1.9862,
  "catégorie NOM" : 0.3701,
  "schéma NOM" : 0.5834,
  "habituel ADJ" : 2.9329,
  "agir VER:impf" : 1.5511,
  "rappeler VER:pres" : 0.7037,
  "coup NOM" : 0.8128,
  "piste NOM" : 0.9262,
  "effet NOM" : 0.4546,
  "chercher VER:pper" : 0.8568,
  "mouvement NOM" : 0.7412,
  "contexte NOM" : 0.7545,
  "repérer VER:infi" : 1.284,
  "complexité NOM" : 0.5131,
  "seul ADJ" : 1.475,
  "expressément ADV" : 1.6871,
  "tête NOM" : 2.6535,
  "écart NOM" : 1.5311,
  "appelé ADJ" : 1.1887,
  "cas NOM" : 0.6461,
  "intégrer VER:infi" : 0.746,
  "élever VER:pper" : 5.8331,
  "cognitif ADJ" : 0.2277,
  "apparition/disparition NOM" : 2.81,
  "adjectif ADJ" : 0.3962,
  "considérer VER:ppre" : 1.1325,
  "émerger VER:cond" : 1.6871,
  "retenir VER:pper" : 0.804,
  "apparaître VER:pper" : 7.3689,
  "devoir VER:impf" : 0.9809,
  "relationnel ADJ" : 0.6069,
  "imposer VER:pres" : 0.9718,
  "détailler VER:pper" : 0.8012,
  "ensemble NOM" : 2.4385,
  "près ADV" : 5.6376,
  "divers ADJ" : 0.4398,
  "exister VER:impf" : 1.7001,
  "distribution NOM" : 1.6787,
  "suivre VER:ppre" : 0.5346,
  "libre ADJ" : 0.8568,
  "type NOM" : 0.3028,
  "transitif ADJ" : 1.0847,
  "prédication NOM" : 2.8857,
  "modifieurs NOM" : 2.4724,
  "conventionnalisées VER:pper" : 1.6871,
  "significativement ADV" : 0.9322,
  "exprimer VER:pres" : 0.6474,
  "nomino ADJ" : 2.4303,
  "récupérer VER:pper" : 1.5284,
  "appliquer VER:pper" : 0.7927,
  "terme NOM" : 3.1164,
  "ailleurs ADV" : 0.6961,
  "pouvoir VER:futu" : 0.564,
  "qualitatif ADJ" : 3.242,
  "moyen NOM" : 0.8903,
  "faire VER:pper" : 1.7783,
  "variation NOM" : 0.3687,
  "simple ADJ" : 0.2243,
  "tel NOM" : 0.8774,
  "autre ADJ" : 2.0961,
  "anticipation NOM" : 2.5093,
  "condition NOM" : 0.4419,
  "qualifier VER:pper" : 1.1867,
  "statistique ADJ" : 1.457,
  "expérience NOM" : 0.2964,
  "marquer VER:pper" : 0.677,
  "g3 NOM" : 4.1292,
  "complétif ADJ" : 1.1945,
  "présenter VER:pres" : 0.2152,
  "détermination NOM" : 3.6166,
  "important ADJ" : 0.5555,
  "slots NOM" : 1.4167,
  "diagnostic NOM" : 1.2253,
  "trouver VER:pres" : 0.3526,
  "seulement ADV" : 2.5416,
  "abstrait ADJ" : 1.9812,
  "permettre VER:ppre" : 0.5339,
  "passage NOM" : 1.4347,
  "toutefois ADV" : 1.1315,
  "lexème NOM" : 6.6932,
  "autrement ADV" : 3.9208,
  "être VER:futu" : 0.6471,
  "contenter VER:infi" : 1.9548,
  "analogie NOM" : 1.1111,
  "exemple NOM" : 0.7888,
  "principe NOM" : 1.0602,
  "accentuer VER:pper" : 1.7491,
  "recevoir VER:pres" : 1.0953,
  "automatiquement ADV" : 0.5672,
  "jonction NOM" : 1.5373,
  "satellite NOM" : 1.6562,
  "proposer VER:infi" : 0.5615,
  "donner VER:pper" : 0.201,
  "résultat NOM" : 0.9893,
  "somme NOM" : 7.15,
  "fin ADJ" : 0.7263,
  "généralisation NOM" : 0.9707,
  "ne ADV" : -2.131
}