{
  "créoliser VER:pper" : 3.2929,
  "idéologie NOM" : 2.8537,
  "prêter VER:pres" : 2.3335,
  "production NOM" : 0.9676,
  "créole NOM" : 3.3042,
  "action NOM" : 1.284,
  "modérer VER:pper" : 2.5889,
  "constituer VER:pres" : 1.1015,
  "extrémité NOM" : 2.7338,
  "dominant ADJ" : 1.9208,
  "afficher VER:pper" : 1.9859,
  "rester VER:pres" : 1.3229,
  "montrer VER:pres" : 1.102,
  "année NOM" : 1.2723,
  "continuum NOM" : 1.9994,
  "auparavant ADV" : 2.8951,
  "comporter VER:pres" : 1.6463,
  "socialement ADV" : 2.1147,
  "fonction NOM" : 1.6444,
  "phonétique NOM" : 3.0821,
  "chaudenson NOM" : 3.2929,
  "archaïque ADJ" : 3.2929,
  "français ADJ" : 6.5001,
  "égard NOM" : 2.2701,
  "trouver VER:pres" : 1.2326,
  "carayol NOM" : 3.2929,
  "premier NOM" : 1.9266,
  "diglossique ADJ" : 2.6282,
  "michel NOM" : 2.816,
  "axe NOM" : 1.6196,
  "symboliquement ADV" : 3.2929,
  "avoir VER:infi" : 1.1062,
  "situer VER:pper" : 1.9243,
  "standard NOM" : 2.1951,
  "éloigner VER:pper" : 1.943,
  "toujours ADV" : 1.3928,
  "acrolectal ADJ" : 3.2929,
  "valorisation NOM" : 2.3974,
  "basilectal ADJ" : 3.0499,
  "école NOM" : 1.5016,
  "remplir VER:pres" : 2.1201,
  "représenter VER:pres" : 1.3844,
  "occuper VER:pres" : 1.6697,
  "survalorisation NOM" : 3.2929,
  "variable ADJ" : 1.5628,
  "ensemble NOM" : 0.8609,
  "mésolecte NOM" : 3.2929,
  "rappeler VER:pres" : 1.6499,
  "étudier VER:ppre" : 2.6341,
  "glottopolitique ADJ" : 2.9656,
  "réunionnais VER:impf" : 2.0516,
  "minorer VER:pper" : 2.5153,
  "pôle NOM" : 7.8538,
  "régional NOM" : 3.2929,
  "position NOM" : 1.0425,
  "contexte NOM" : 0.6975,
  "reconnaître VER:pper" : 1.9063,
  "département NOM" : 3.2929,
  "robert NOM" : 1.5998,
  "appliquer VER:pper" : 1.7472,
  "théorie NOM" : 1.0848,
  "dérouler VER:pres" : 1.81,
  "noble ADJ" : 3.2929,
  "imprégner VER:pper" : 2.4847,
  "ne ADV" : -0.1489,
  "continuellement ADV" : 3.2929,
  "comparer VER:pper" : 1.8684
}