{
  "vouloir VER:pres" : 1.7599,
  "former VER:pres" : 1.9953,
  "défini ADJ" : 1.9816,
  "distance NOM" : 1.2287,
  "définir VER:infi" : 2.7494,
  "brut ADJ" : 1.912,
  "venir VER:pres" : 1.4141,
  "item NOM" : 1.3156,
  "suffisant ADJ" : 3.6725,
  "présent ADJ" : 1.0359,
  "dessous NOM" : 3.7856,
  "cas NOM" : 0.5372,
  "locution NOM" : 2.0567,
  "valeur NOM" : 7.7011,
  "langue NOM" : 0.3657,
  "circonstanciel ADJ" : 7.6415,
  "correspondre VER:ppre" : 1.4835,
  "courant ADJ" : 1.6159,
  "spécialiser VER:pper" : 1.4567,
  "réduction NOM" : 2.0747,
  "silence NOM" : 2.5075,
  "souple ADJ" : 2.5557,
  "forme NOM" : 0.5221,
  "être VER:pres" : -0.2138,
  "plus ADV" : 0.2013,
  "restriction NOM" : 2.2656,
  "discours NOM" : 0.7982,
  "facteur NOM" : 1.2215,
  "adverbial ADJ" : 1.2802,
  "séquence NOM" : 0.9803,
  "façon NOM" : 0.9505,
  "considérer VER:pper" : 1.1346,
  "très ADV" : 0.6341,
  "droite NOM" : 1.8541,
  "borner VER:ppre" : 3.0697,
  "apposition NOM" : 2.7367,
  "nombre NOM" : 0.7968,
  "pas ADV" : 0.2789,
  "non ADV" : 0.6283,
  "laisser VER:pres" : 1.8297,
  "également ADV" : 0.848,
  "pied NOM" : 2.61,
  "unité NOM" : 0.8031,
  "verbal ADJ" : 0.8568,
  "circonscrire VER:infi" : 2.6043,
  "manière NOM" : 1.0068,
  "prépositionnel ADJ" : 1.5166,
  "lexical ADJ" : 0.4702,
  "toutefois ADV" : 1.3378,
  "atténuation NOM" : 2.6926,
  "permettre VER:pres" : 0.6198,
  "ainsi ADV" : 0.6643,
  "taille NOM" : 1.3247,
  "bruit NOM" : 1.9344,
  "groupe NOM" : 0.9259,
  "couvrir VER:infi" : 2.6277,
  "* ADJ" : 2.5214,
  "avoir VER:pres" : -0.2411,
  "rajouter VER:infi" : 2.6788,
  "schéma NOM" : 1.002,
  "occurrence NOM" : 2.4075,
  "score NOM" : 1.3967,
  "suivant ADJ" : 1.2024,
  "nominal ADJ" : 1.2675,
  "aval NOM" : 2.3124,
  "meilleur ADJ" : 1.4078,
  "complexe ADJ" : 1.016,
  "tentative NOM" : 1.9723,
  "généralement ADV" : 1.2874,
  "complément NOM" : 3.0385,
  "type NOM" : 0.4929,
  "effet NOM" : 0.7,
  "proposer VER:pper" : 1.08,
  "consécutif ADJ" : 2.1476,
  "ainsi_que NOM" : 1.6102,
  "méthode NOM" : 0.9851,
  "moyen ADJ" : 1.1946,
  "surface NOM" : 1.8918,
  "comme ADV" : 3.3569,
  "plupart NOM" : 1.331,
  "résiduel ADJ" : 2.9407,
  "ne ADV" : 0.5206,
  "terme NOM" : 1.4275,
  "insertion NOM" : 2.1536,
  "patron NOM" : 1.7943,
  "lire VER:pres" : 3.2805,
  "rechercher VER:pres" : 2.4246,
  "syntagme NOM" : 1.2761
}