{
  "popper NOM" : 2.1662,
  "dire VER:ppre" : 1.5095,
  "présupposer VER:ppre" : 2.1662,
  "production NOM" : 0.4052,
  "purement ADV" : 1.2069,
  "illocutoire ADJ" : 2.6589,
  "qualifier VER:cond" : 2.5132,
  "constituer VER:pres" : 0.5179,
  "cri NOM" : 11.4404,
  "prédictible ADJ" : 2.6002,
  "aussi ADV" : 0.2288,
  "hypothèse NOM" : 0.3147,
  "sémiotique ADJ" : 1.3757,
  "norme NOM" : 1.7022,
  "réponse NOM" : 0.4221,
  "amont NOM" : 1.7161,
  "informateur NOM" : 2.1323,
  "forme NOM" : 1.1677,
  "fait NOM" : 0.3275,
  "nécessaire ADJ" : 0.5348,
  "description NOM" : 0.4048,
  "dewaal NOM" : 2.1662,
  "propre ADJ" : 0.9723,
  "métaphorique ADJ" : 0.8749,
  "précéder VER:pres" : 1.0913,
  "matériaux NOM" : 3.9296,
  "affect NOM" : 0.9602,
  "être VER:infi" : 0.853,
  "appartiendraiant VER:ppre" : 2.1662,
  "rictus NOM" : 2.044,
  "locuteur NOM" : 0.3585,
  "pouvoir VER:cond" : 1.3806,
  "énonciateur NOM" : 1.1718,
  "global ADJ" : 0.7567,
  "constater VER:pres" : 1.0141,
  "réaction NOM" : 1.5957,
  "imaginer VER:pres" : 3.1744,
  "trouver VER:pper" : 1.0745,
  "textuel ADJ" : 0.5992,
  "manière NOM" : 0.4473,
  "valorisation NOM" : 1.7584,
  "présentatif NOM" : 3.8913,
  "pur ADJ" : 1.3868,
  "avoir VER:subp" : 1.09,
  "phonétique ADJ" : 1.4964,
  "domaine NOM" : 0.3176,
  "inanalysable ADJ" : 1.9708,
  "valider VER:pper" : 6.4102,
  "avoir VER:pres" : -0.5845,
  "élaboration NOM" : 2.17,
  "que ADV" : 0.9578,
  "aval NOM" : 1.6862,
  "arrière-plan NOM" : 5.3764,
  "attestation NOM" : 3.7992,
  "situation NOM" : 2.1002,
  "aller VER:pres" : 0.4922,
  "modèle NOM" : -0.2304,
  "perspective NOM" : 0.8413,
  "physiologique ADJ" : 2.0058,
  "présent NOM" : 0.7791,
  "exiger VER:pres" : 1.5933,
  "sensation NOM" : 1.3515,
  "évidemment ADV" : 1.2607,
  "contenir VER:pres" : 1.0693,
  "abri NOM" : 2.2878,
  "partir VER:infi" : 0.2922,
  "comme ADV" : 0.7301,
  "pré-intentionnel NOM" : 2.5132,
  "expression NOM" : 0.6605,
  "admirable ADJ" : 2.1662,
  "Donald NAM" : 1.5133,
  "narratologiques ADJ" : 2.6002,
  "nommer VER:pres" : 1.661,
  "espèce NOM" : 1.4286,
  "présence NOM" : 0.6356,
  "stable ADJ" : 2.4553,
  "croyance NOM" : 3.2773,
  "impliquer VER:pres" : 1.0198,
  "stratégie NOM" : 0.628,
  "similaire ADJ" : 1.0085,
  "lexicographique ADJ" : 0.924,
  "utilisateur NOM" : 0.2126,
  "produit NOM" : 1.6196,
  "précis ADJ" : 0.7242,
  "ensuite ADV" : 0.6052,
  "objet NOM" : 0.3125,
  "source NOM" : 1.6347,
  "mécanisme NOM" : 0.9434,
  "auto-représentation NOM" : 2.1662,
  "même ADV" : 0.8551,
  "autant ADV" : 1.7334,
  "correspondre VER:ppre" : 0.8772,
  "souffrance NOM" : 1.7687,
  "proprement ADV" : 1.2238,
  "fondamental ADJ" : 1.0192,
  "être VER:pres" : 0.3203,
  "plus ADV" : -0.4057,
  "consister VER:pres" : 0.6586,
  "être VER:ppre" : 0.438,
  "évolutionniste ADJ" : 2.1662,
  "pouvoir VER:infi" : 1.0024,
  "lexique NOM" : 0.2615,
  "déjà ADV" : 0.6509,
  "niveau NOM" : 0.4605,
  "même ADJ" : 0.4383,
  "générer VER:infi" : 1.9938,
  "demeurer VER:pres" : 1.2855,
  "pas ADV" : 0.9937,
  "but NOM" : 0.9249,
  "virtuellement ADV" : 2.6002,
  "décrire VER:pper" : 0.6471,
  "non ADV" : 0.4998,
  "relation NOM" : -0.3544,
  "ici ADV" : 0.2878,
  "opération NOM" : 0.8651,
  "noter VER:pper" : 1.1506,
  "mieux ADV" : 0.7837,
  "relier VER:infi" : 2.0374,
  "causal ADJ" : 2.3934,
  "éventualité NOM" : 2.6793,
  "linguistique ADJ" : 1.5499,
  "contenu NOM" : 16.1193,
  "collectif ADJ" : 1.0146,
  "nécessairement ADV" : 1.0198,
  "lors ADV" : 0.4975,
  "là ADV" : 0.7737,
  "agir VER:pres" : 0.4317,
  "convention NOM" : 1.7255,
  "tendre VER:pres" : 1.2811,
  "schéma NOM" : 0.4433,
  "validable ADJ" : 4.51,
  "question NOM" : 0.3329,
  "étape NOM" : 0.5123,
  "effet NOM" : 0.2128,
  "funèbre ADJ" : 2.1662,
  "sorte NOM" : 2.2044,
  "fonctionnel ADJ" : 1.2305,
  "propositionnel ADJ" : 6.4145,
  "oublier VER:infi" : 1.6834,
  "illimiter VER:pper" : 2.4577,
  "douleur NOM" : 3.6789,
  "extrêmement ADV" : 1.1769,
  "crispation NOM" : 2.044,
  "exclamatif ADJ" : 5.4582,
  "donc ADV" : 0.3902,
  "seul ADJ" : 0.3794,
  "lumière NOM" : 1.5095,
  "choix NOM" : 0.5027,
  "mémoire NOM" : 1.0852,
  "respecter VER:pres" : 1.5864,
  "réduire VER:pres" : 1.7255,
  "partir VER:pres" : 1.6075,
  "comme-si NOM" : 1.9131,
  "stimulus NOM" : 4.003,
  "faire VER:pres" : 0.255,
  "asserter VER:pper" : 1.9708,
  "applicable ADJ" : 1.5621,
  "brut ADJ" : 1.2911,
  "fascicule NOM" : 5.5457,
  "intentionnel ADJ" : 8.7808,
  "institutionnel ADJ" : 1.5686,
  "localisation NOM" : 1.8452,
  "effectuer VER:infi" : 1.0969,
  "mental ADJ" : 1.0866,
  "interprétation NOM" : 0.737,
  "cas NOM" : 0.3679,
  "placer VER:infi" : 1.8328,
  "devoir VER:pres" : 0.3266,
  "énoncé NOM" : 1.9633,
  "traitement NOM" : 0.4118,
  "classe NOM" : 0.333,
  "cognitif ADJ" : 1.2043,
  "lier VER:pper" : 0.5267,
  "représentation NOM" : 0.487,
  "relever VER:pper" : 1.0539,
  "réaliser VER:infi" : 0.9524,
  "relativement ADV" : 1.0609,
  "grand ADJ" : 0.2557,
  "discours NOM" : 0.2821,
  "ranger VER:infi" : 1.9998,
  "voire ADV" : 0.7819,
  "mimer VER:pper" : 2.1662,
  "corps NOM" : 1.1916,
  "immédiat ADJ" : 1.1934,
  "large ADJ" : 0.7719,
  "notation NOM" : 1.3784,
  "penser VER:pres" : 1.34,
  "pouvoir VER:pres" : 0.8778,
  "tour NOM" : 1.2354,
  "rapport NOM" : 0.3265,
  "confondre VER:infi" : 1.9281,
  "édifier VER:pper" : 2.1662,
  "interjection NOM" : 2.7002,
  "détailler VER:pper" : 1.1273,
  "mettre VER:pper" : 0.4749,
  "rédacteur NOM" : 1.0673,
  "métaphoriquement ADV" : 2.1242,
  "permettre VER:infi" : 0.8721,
  "évident ADJ" : 1.0667,
  "postuler VER:infi" : 1.6638,
  "enquête NOM" : 2.3278,
  "être VER:impf" : 0.4798,
  "expressif ADJ" : 9.2755,
  "occurrence NOM" : 0.4904,
  "incarner VER:pper" : 2.1662,
  "nature NOM" : 0.5945,
  "créateur ADJ" : 2.6002,
  "métaphore NOM" : 0.8741,
  "type NOM" : 0.3086,
  "chercher VER:pres" : 1.0699,
  "côté NOM" : 1.5348,
  "donner VER:pres" : 0.6257,
  "resémantisation NOM" : 2.3507,
  "particulier ADJ" : 0.5513,
  "capacité NOM" : 2.0529,
  "contraire NOM" : 0.7899,
  "-ci ADV" : 0.4864,
  "publier VER:pper" : 1.482,
  "terme NOM" : -0.2008,
  "psychologique ADJ" : 1.149,
  "référence NOM" : 0.8421,
  "évolution NOM" : 0.7466,
  "phrase NOM" : -0.2395,
  "venir VER:pres" : 0.8119,
  "searle NOM" : 6.6835,
  "difficulté NOM" : 0.4475,
  "tel NOM" : 2.7076,
  "simple ADJ" : 1.1947,
  "autre ADJ" : 0.5684,
  "tomasello NAM" : 1.6347,
  "scène NOM" : 1.0308,
  "damasio NOM" : 1.523,
  "base NOM" : 1.2709,
  "ancien ADJ" : 1.527,
  "état NOM" : 1.4833,
  "transposable ADJ" : 2.1662,
  "expliquer VER:infi" : 0.9931,
  "pourvu ADJ" : 10.6398,
  "version NOM" : 0.8632,
  "présupposer VER:pper" : 1.6834,
  "abord NOM" : 0.657,
  "véritable ADJ" : 2.3986,
  "phénomène NOM" : 1.8047,
  "adresser VER:infi" : 1.7069,
  "considérer VER:pper" : 0.5571,
  "très ADV" : -0.1612,
  "cause NOM" : 0.8617,
  "différence NOM" : 0.4114,
  "solution NOM" : 2.1866,
  "questionnaire NOM" : 1.1419,
  "postuler VER:pres" : 1.1266,
  "sens NOM" : 0.4231,
  "assertif ADJ" : 1.7903,
  "scénario NOM" : 0.9905,
  "avoir VER:infi" : 0.522,
  "créatif ADJ" : 2.0309,
  "connaître VER:pres" : 1.068,
  "pourvu NOM" : 2.5132,
  "toutefois ADV" : 0.7408,
  "provoquer VER:pper" : 1.8494,
  "déictique ADJ" : 1.6503,
  "proximité NOM" : 1.3464,
  "rhétorique ADJ" : 1.5057,
  "desservir VER:infi" : 2.6002,
  "être VER:futu" : 0.4792,
  "remplir VER:pper" : 1.8494,
  "comprendre VER:pres" : 2.6114,
  "espace NOM" : 0.7354,
  "posséder VER:pres" : 3.8808,
  "primitif ADJ" : 1.6777,
  "exemple NOM" : 0.4878,
  "naître VER:cond" : 2.5132,
  "signifier VER:pres" : 1.2286,
  "complexe ADJ" : 0.455,
  "arracher VER:pper" : 2.1662,
  "expressivité NOM" : 2.0058,
  "si ADV" : 0.7099,
  "exprimer VER:infi" : 2.1974,
  "caractéristique NOM" : 0.5908,
  "paysage NOM" : 1.7255,
  "proposer VER:pper" : 0.5096,
  "véhiculer VER:pres" : 1.4732,
  "commentaire NOM" : 1.5887,
  "posséder VER:impf" : 2.1662,
  "véhiculer VER:ppre" : 2.1662,
  "représentatif ADJ" : 1.8091,
  "son NOM" : 1.206,
  "éloge NOM" : 2.1662,
  "football NOM" : 1.3926,
  "auditoire NOM" : 1.7449,
  "acte NOM" : 4.5388,
  "contenir VER:pper" : 1.4193,
  "supposer VER:pres" : 2.5237,
  "date NOM" : 1.8667,
  "ne ADV" : 1.3103,
  "formation NOM" : 1.0752,
  "opposition NOM" : 1.2866,
  "singulier ADJ" : 2.5774,
  "palette NOM" : 2.1662,
  "comme-si VER:pper" : 2.1662,
  "fortement ADV" : 1.1562
}