{
  "system NOM" : 1.756,
  "rigid NOM" : 2.5258,
  "semi ADJ" : 2.6506,
  "particular NOM" : 1.8248,
  "the VER:futu" : 1.1318,
  "depending NOM" : 2.5258,
  "this NOM" : 2.2763,
  "own NOM" : 2.6506,
  "research NAM" : 1.964,
  "between NOM" : 1.8218,
  "the NOM" : 1.7746,
  "task ADJ" : 2.1382,
  "given ADJ" : 2.4481,
  "linguistic NOM" : 1.6695,
  "varied VER:pres" : 2.5258,
  "the VER:simp" : 2.5055,
  "operational ADJ" : 2.151,
  "linguists NOM" : 2.6506,
  "the ADJ" : 1.1698,
  "their NOM" : 3.2232,
  "and VER:subi" : 3.9211,
  "assists NOM" : 2.6506,
  "information NOM" : 0.6201,
  "text VER:futu" : 2.5258,
  "that NOM" : 4.6633,
  "of VER:simp" : 1.4449,
  "and ADJ" : 1.7997,
  "should NOM" : 4.6144,
  "classification NOM" : 1.3097,
  "in ADJ" : 8.6929,
  "corpus NOM" : 1.3042,
  "both NOM" : 1.9703,
  "avoir VER:pres" : 3.1696,
  "beyond ADJ" : 2.5258,
  "text VER:pper" : 1.9878,
  "different VER:simp" : 1.8233,
  "support NOM" : 1.3805,
  "corpora VER:simp" : 6.0917,
  "texts ADJ" : 1.6879,
  "two NOM" : 3.8934,
  "which NOM" : 1.3155,
  "leads NOM" : 2.3202,
  "engineers NOM" : 2.6506,
  "better NOM" : 2.5258,
  "tool NOM" : 2.5258,
  "of VER:pper" : 1.3304,
  "when NOM" : 1.8581,
  "abstract NOM" : 1.2041,
  "results NOM" : 1.7705,
  "pattern NOM" : 8.6836,
  "contribute VER:pres" : 2.5258,
  "modelling NOM" : 5.0082,
  "extraction NOM" : 2.9859,
  "the VER:subi" : 0.8147,
  "eight NOM" : 2.5258,
  "efficiency ADJ" : 2.5258,
  "from NOM" : 6.9986,
  "unique ADJ" : 1.2827,
  "scope NOM" : 2.5258,
  "with NOM" : 1.575,
  "knowledge ADJ" : 1.9812,
  "corpora NOM" : 2.0904,
  "discipline NOM" : 1.7997,
  "nlp NOM" : 5.7248,
  "should NAM" : 2.5258,
  "obtained ADJ" : 2.214,
  "by NOM" : 1.2835,
  "conclusion NOM" : 1.3142,
  "characterisation NOM" : 2.5258,
  "test NOM" : 0.9147,
  "present VER:pres" : 2.0202,
  "base NOM" : 0.5603,
  "about NOM" : 1.7224,
  "appropriate ADJ" : 2.5258,
  "to NOM" : 1.8159,
  "relationship NOM" : 2.3299,
  "we ADJ" : 3.239,
  "an NOM" : 0.8123,
  "involved ADJ" : 2.4747,
  "characterise ADJ" : 2.6506,
  "revealing NOM" : 2.6506,
  "these NOM" : 1.5666,
  "of ADJ" : 1.4686,
  "semantic NOM" : 1.9556,
  "electronic ADJ" : 2.4481,
  "for NOM" : 4.0318,
  "experiment VER:pres" : 2.6506,
  "relationships NOM" : 2.6506,
  "requires ADJ" : 2.6506,
  "evaluating NOM" : 4.2405,
  "paper NOM" : 1.7458,
  "go ADV" : 2.4416,
  "relation NOM" : 1.4509,
  "ontology ADJ" : 2.5258,
  "lexical ADJ" : 0.3102,
  "our VER:subi" : 2.3878,
  "report NOM" : 4.3305,
  "engineering NOM" : 2.2659,
  "identification NOM" : 1.2748,
  "collaboration NOM" : 4.0774,
  "user NOM" : 2.5258,
  "automatic ADJ" : 2.6506,
  "text VER:subi" : 2.1414,
  "set NOM" : 1.7626,
  "defining NOM" : 2.6506,
  "definition NOM" : 1.9768,
  "caméléon NOM" : 2.4598,
  "must NOM" : 2.5258,
  "and VER:simp" : 1.1083,
  "used ADJ" : 1.7997,
  "be VER:subi" : 3.0356,
  "the VER:pper" : 0.9529,
  "cross-disciplinary ADJ" : 5.0082,
  "of VER:subi" : 3.4772,
  "tuning NOM" : 4.8737,
  "provided ADJ" : 2.1676,
  "through ADJ" : 2.1956,
  "genre NOM" : 0.7666,
  "pieces ADJ" : 2.5258,
  "behaviours NOM" : 2.6506,
  "strongly ADJ" : 2.5258
}