{
  "confusion NOM" : 2.0888,
  "montrer VER:infi" : 0.9773,
  "personne NOM" : 0.5429,
  "bouleversement NOM" : 2.5052,
  "comment ADV" : 0.7702,
  "merida NOM" : 2.5052,
  "interpréter VER:pper" : 1.159,
  "provisoire ADJ" : 1.9872,
  "nécessaire ADJ" : 1.4405,
  "règles NOM" : 0.8046,
  "paraître VER:pres" : 1.0315,
  "dynamique ADJ" : 0.9532,
  "empirique ADJ" : 0.9262,
  "assimiler VER:pres" : 1.9443,
  "mémoriser VER:pper" : 1.4889,
  "pédagogie NOM" : 1.8618,
  "serait-il VER:cond" : 1.7863,
  "produire VER:pres" : 1.1881,
  "conceptuel ADJ" : 0.7092,
  "compter VER:pres" : 0.7962,
  "possibilité NOM" : 0.8784,
  "lettre NOM" : 5.6467,
  "albert NOM" : 2.6647,
  "représenter VER:pres" : 0.832,
  "réglementer VER:infi" : 2.4018,
  "souhaitable ADJ" : 1.897,
  "zone NOM" : 1.0164,
  "identifier VER:pper" : 0.9612,
  "lambert-félix NOM" : 2.1885,
  "raisonner VER:infi" : 1.8889,
  "minimal ADJ" : 1.1873,
  "fautif ADJ" : 4.1936,
  "disponible ADJ" : 0.8784,
  "cadre NOM" : 0.4223,
  "tenant NOM" : 1.7473,
  "perspective NOM" : 0.9013,
  "changement NOM" : 0.5845,
  "quantité NOM" : 4.3473,
  "infini ADJ" : 2.5052,
  "mesure NOM" : 0.4031,
  "vision NOM" : 1.3143,
  "allégrement ADV" : 2.3407,
  "véhiculer VER:infi" : 1.9178,
  "bond NOM" : 2.6647,
  "évoluer VER:pres" : 1.6434,
  "diversité NOM" : 0.925,
  "écrire VER:infi" : 0.8956,
  "entraîner VER:pres" : 1.9178,
  "extrait NOM" : 1.424,
  "constituer VER:pper" : 0.8995,
  "construire VER:infi" : 0.9147,
  "romani NOM" : 2.5052,
  "problématique ADJ" : 1.4473,
  "constituer VER:infi" : 1.3496,
  "diglossie NOM" : 1.2343,
  "dire VER:pper" : 0.7886,
  "fijalkow VER:simp" : 2.6647,
  "prénom NOM" : 1.4006,
  "compétence NOM" : 0.8992,
  "réaliser VER:pres" : 1.1661,
  "interlecte NOM" : 5.3456,
  "intérieur NOM" : 1.2369,
  "répandre VER:pper" : 1.8656,
  "produire VER:pper" : 0.6051,
  "acrolectale ADJ" : 2.2973,
  "parvenir VER:futu" : 2.4018,
  "sémiographique ADJ" : 2.6647,
  "atteindre VER:infi" : 0.9262,
  "lors ADV" : 0.5512,
  "preuve NOM" : 1.3994,
  "conséquent ADJ" : 0.8736,
  "quantitatif ADJ" : 1.3386,
  "pôle NOM" : 1.777,
  "pédagogique ADJ" : 1.4321,
  "familial ADJ" : 1.777,
  "sensibiliser VER:infi" : 1.9822,
  "cesser VER:pres" : 1.9443,
  "parole NOM" : 0.797,
  "différencier VER:pres" : 1.5927,
  "appliquer VER:pres" : 1.2235,
  "sorte NOM" : 1.0204,
  "maximum ADJ" : 1.5638,
  "regard NOM" : 1.1452,
  "kessler NOM" : 2.6647,
  "récuser VER:pres" : 2.5052,
  "homogène ADJ" : 1.3773,
  "bourasse NOM" : 2.6647,
  "créolophone ADJ" : 1.8399,
  "exposer VER:pres" : 1.8694,
  "respecter VER:ppre" : 1.8849,
  "mélanger VER:infi" : 2.0581,
  "étendre VER:infi" : 1.424,
  "faire VER:pres" : 0.2983,
  "transfert NOM" : 1.3667,
  "calquer VER:pper" : 2.4579,
  "ferreiro NOM" : 9.1856,
  "milieu NOM" : 0.9826,
  "graphie NOM" : 1.0455,
  "diversifier VER:pper" : 1.7063,
  "tard ADV" : 1.4445,
  "read NOM" : 2.6647,
  "énoncé NOM" : 0.2855,
  "objectif NOM" : 1.2097,
  "tolérance NOM" : 2.1576,
  "traitement NOM" : 0.4628,
  "panel NOM" : 2.2579,
  "former VER:infi" : 1.6713,
  "lier VER:pper" : 0.5813,
  "aberration NOM" : 2.4018,
  "écriture NOM" : 0.5676,
  "mélange NOM" : 3.8145,
  "pouvoir VER:ppre" : 1.1052,
  "grammatical ADJ" : 0.5616,
  "permanent ADJ" : 1.5867,
  "jeter VER:pres" : 2.5052,
  "moins ADV" : 0.9347,
  "épistémologique ADJ" : 1.5947,
  "fur NOM" : 1.56,
  "maintenant ADV" : 1.231,
  "situer VER:pper" : 1.3541,
  "besse NOM" : 5.042,
  "chercheur NOM" : 1.054,
  "communication NOM" : 1.7765,
  "agir VER:infi" : 1.6302,
  "chomsky NOM" : 1.5163,
  "archétypique ADJ" : 2.4018,
  "gomez VER:pres" : 4.6089,
  "parler VER:infi" : 1.0605,
  "nature NOM" : 1.5686,
  "notion NOM" : 0.6192,
  "d ADJ" : 1.8656,
  "possible ADJ" : 0.459,
  "treiman NOM" : 2.6647,
  "substitution NOM" : 2.2486,
  "fergusonienne ADJ" : 2.5052,
  "acquérir VER:pper" : 1.1896,
  "ordre NOM" : 0.7979,
  "juger VER:pres" : 1.7589,
  "mélanger VER:pres" : 3.8028,
  "basilecte NOM" : 2.5052,
  "échec NOM" : 1.6048,
  "enseignant NOM" : 3.4448,
  "confronter VER:pper" : 1.6007,
  "subir VER:infi" : 2.1287,
  "penser VER:infi" : 1.5527,
  "palaccio NOM" : 4.6089,
  "apprentissage NOM" : 0.9821,
  "aléatoire ADJ" : 1.5163,
  "spécifique ADJ" : 0.4147,
  "créole NOM" : 8.4287,
  "difficulté NOM" : 0.4997,
  "objectivement ADV" : 2.0824,
  "démontrer VER:infi" : 1.639,
  "routine NOM" : 2.5052,
  "grammaire NOM" : 0.5277,
  "système NOM" : -0.3323,
  "minimum NOM" : 1.774,
  "rejeter VER:pres" : 1.9628,
  "expliquer VER:infi" : 1.0545,
  "apprenant NOM" : 0.8977,
  "entreprendre VER:infi" : 2.0824,
  "manifestation NOM" : 1.4721,
  "nucléaire ADJ" : 2.3641,
  "abord NOM" : 1.7012,
  "mêler VER:infi" : 2.5052,
  "règlement NOM" : 2.5052,
  "demander VER:infi" : 1.3257,
  "réunion NOM" : 1.8656,
  "ajuster VER:ppre" : 2.2579,
  "intermédiaire ADJ" : 1.6713,
  "obéir VER:pres" : 1.8434,
  "forger VER:pres" : 2.5052,
  "nombre NOM" : 1.5695,
  "séparation NOM" : 1.9872,
  "changer VER:ppre" : 2.6647,
  "côtoyer VER:pres" : 2.2772,
  "fijalkow NOM" : 1.8889,
  "autrement ADV" : 2.3769,
  "permettre VER:pres" : 0.5741,
  "contrainte NOM" : 0.8071,
  "réunionnais NOM" : 2.5052,
  "graphique ADJ" : 1.1228,
  "comprendre VER:ppre" : 1.9264,
  "contenter VER:infi" : 2.3641,
  "jaffré VER:pper" : 1.508,
  "réunionnais VER:impf" : 5.214,
  "conflit NOM" : 1.6761,
  "macro-système NOM" : 2.1885,
  "caractéristique NOM" : 0.6469,
  "systématique ADJ" : 0.9715,
  "savoir VER:ppre" : 1.6935,
  "frontière NOM" : 1.2446,
  "inventer VER:pper" : 1.9534,
  "image NOM" : 0.8137,
  "viol NOM" : 2.5052,
  "étude NOM" : 0.1992,
  "sociolinguistique ADJ" : 1.4174,
  "outre ADV" : 0.9663,
  "offrir VER:pres" : 1.0077
}