{
  "potentiel NOM" : 1.9008,
  "imagé ADJ" : 2.5917,
  "bouleversement NOM" : 2.6538,
  "merida NOM" : 2.6538,
  "propreté NOM" : 2.5917,
  "hybridation NOM" : 2.0532,
  "provisoire ADJ" : 2.1354,
  "manuel ADJ" : 1.4758,
  "métaphorique ADJ" : 7.418,
  "vulgarisation NOM" : 6.7109,
  "égard NOM" : 3.9901,
  "style NOM" : 1.7541,
  "constat NOM" : 1.5081,
  "agricole ADJ" : 1.7908,
  "zone NOM" : 1.159,
  "pencher VER:infi" : 1.9502,
  "bricoleur NOM" : 2.6374,
  "lambert-félix NOM" : 2.3369,
  "fautif ADJ" : 2.0923,
  "prudent ADJ" : 6.2859,
  "puiser VER:pper" : 2.3211,
  "véhiculer VER:pper" : 1.8116,
  "schlanger ADJ" : 2.6374,
  "infini ADJ" : 2.6538,
  "allégrement ADV" : 2.4892,
  "vision NOM" : 1.46,
  "rendre VER:pper" : 1.6581,
  "entraîner VER:pres" : 2.0658,
  "romani NOM" : 2.6538,
  "catégorisation NOM" : 1.6784,
  "conceptualiser VER:pres" : 2.6374,
  "vérifier VER:pres" : 1.7541,
  "alphabétique ADJ" : 1.6943,
  "excellent ADJ" : 2.0369,
  "pensée NOM" : 1.5246,
  "interlecte NOM" : 1.6698,
  "médical ADJ" : 3.7083,
  "emprunter VER:infi" : 2.6374,
  "rien ADV" : 1.7953,
  "acrolectale ADJ" : 2.4458,
  "imager VER:pper" : 2.5917,
  "dénomination NOM" : 2.7126,
  "greffe NOM" : 5.4257,
  "rastier ADJ" : 2.5917,
  "agriculture NOM" : 5.5264,
  "sorte NOM" : 1.163,
  "récuser VER:pres" : 2.6538,
  "exposer VER:pres" : 2.0173,
  "respecter VER:ppre" : 2.0329,
  "fascicule NOM" : 1.7999,
  "finance NOM" : 2.5917,
  "former VER:infi" : 1.8187,
  "dispos ADJ" : 2.5917,
  "mélange NOM" : 1.9037,
  "pouvoir VER:ppre" : 1.2489,
  "répertoire NOM" : 1.4196,
  "permanent ADJ" : 1.7339,
  "langagier ADJ" : 0.8188,
  "simplifier VER:infi" : 2.3289,
  "jeter VER:pres" : 2.6538,
  "dépouillement NOM" : 2.467,
  "arabe ADJ" : 2.5751,
  "retenir VER:pper" : 1.3373,
  "communication NOM" : 0.503,
  "transplantation NOM" : 3.396,
  "occurrence NOM" : 0.6726,
  "note NOM" : 1.7127,
  "métaphore NOM" : 7.4138,
  "rapporter VER:pper" : 2.2063,
  "attendre VER:cond" : 2.5917,
  "substitution NOM" : 2.3971,
  "fergusonienne ADJ" : 2.6538,
  "mélanger VER:pres" : 1.8979,
  "sec ADJ" : 1.6548,
  "basilecte NOM" : 2.6538,
  "couture NOM" : 2.5917,
  "organe NOM" : 2.049,
  "créole NOM" : 2.4599,
  "histoire NOM" : 1.1133,
  "index NOM" : 1.7819,
  "légion NOM" : 2.5917,
  "rejeter VER:pres" : 2.1109,
  "pourvu ADJ" : 1.9186,
  "courant ADJ" : 1.2082,
  "emprise NOM" : 2.3369,
  "nucléaire ADJ" : 2.5127,
  "structurer VER:pres" : 1.8979,
  "mêler VER:infi" : 2.6538,
  "règlement NOM" : 2.6538,
  "intermédiaire ADJ" : 1.8187,
  "forger VER:pres" : 2.6538,
  "obéir VER:pres" : 1.9913,
  "carte NOM" : 1.8781,
  "réunionnais NOM" : 2.6538,
  "pulluler VER:pres" : 2.5917,
  "rapporter VER:pres" : 1.6419,
  "arabe NOM" : 1.4498,
  "réunionnais VER:impf" : 1.6263,
  "conflit NOM" : 1.8236,
  "macro-système NOM" : 2.3369,
  "accessible ADJ" : 1.4779,
  "sémiotisent VER:subp" : 2.6374,
  "juste ADJ" : 1.3498,
  "commentaire NOM" : 1.7999,
  "viol NOM" : 2.6538,
  "métaphorisation NOM" : 1.4779,
  "sociolinguistique ADJ" : 1.5637,
  "priori ADV" : 1.1142,
  "conceptualisation NOM" : 1.7184
}